[{"compare":"1MAR1915","coords":[0.0,0.0],"count":5,"date":"1 Mar 1919","datetime":"1919-03-01T00:00:00.000Z","group":"GWD00000r0","hit_rate":1.0,"id":"597b2e87909f050004000002","label":"1 Mar 1919","page":"AWD0003rq1","page_number":2,"page_order":2,"page_type":"diary","place":"","subject_id":"59539e059d936f003e003979","time":"","type":"diaryDate","votes":{"day":["1"],"month":["Mar"],"year":["1919"]},"x":6,"y":25},{"compare":"CATTERICK","coords":[0.0,0.0],"count":2,"date":"1 Mar 1919","datetime":"1919-03-01T00:00:00.000Z","group":"GWD00000r0","hit_rate":0.4,"id":"597b2e87909f050004000003","label":"Catterick","page":"AWD0003rq1","page_number":2,"page_order":3,"page_type":"diary","place":"Catterick","subject_id":"59539e059d936f003e003979","time":"","type":"place","votes":{"place":["Catterick"],"location":["true"],"name":["Catterick Camp","Catterick"],"lat":["54.35","54.37542"],"long":["-1.71667","-1.63328"],"id":["2653497","2653499"]},"x":6,"y":27},{"compare":"2MAR1919","coords":[0.0,0.0],"count":3,"date":"2 Mar 1919","datetime":"1919-03-02T00:00:00.000Z","group":"GWD00000r0","hit_rate":0.6,"id":"597b2e87909f050004000006","label":"2 Mar 1919","page":"AWD0003rq1","page_number":2,"page_order":6,"page_type":"diary","place":"Catterick","subject_id":"59539e059d936f003e003979","time":"","type":"diaryDate","votes":{"day":["2"],"month":["Mar"],"year":["1919"]},"x":6,"y":32},{"compare":"3MAR1919","coords":[0.0,0.0],"count":4,"date":"3 Mar 1919","datetime":"1919-03-03T00:00:00.000Z","group":"GWD00000r0","hit_rate":0.8,"id":"597b2e87909f050004000007","label":"3 Mar 1919","page":"AWD0003rq1","page_number":2,"page_order":7,"page_type":"diary","place":"Catterick","subject_id":"59539e059d936f003e003979","time":"","type":"diaryDate","votes":{"day":["3"],"month":["Mar"],"year":["1919"]},"x":6,"y":35},{"compare":"1030AM","coords":[0.0,0.0],"count":2,"date":"3 Mar 1919","datetime":"1919-03-03T10:30:00.000Z","group":"GWD00000r0","hit_rate":0.4,"id":"597b2e88909f050004000008","label":"1030AM","page":"AWD0003rq1","page_number":2,"page_order":8,"page_type":"diary","place":"Catterick","subject_id":"59539e059d936f003e003979","time":"1030AM","type":"time","votes":{},"x":17,"y":35},{"compare":"0500PM","coords":[0.0,0.0],"count":3,"date":"3 Mar 1919","datetime":"1919-03-03T17:00:00.000Z","group":"GWD00000r0","hit_rate":0.6,"id":"597b2e88909f05000400000b","label":"0500PM","page":"AWD0003rq1","page_number":2,"page_order":11,"page_type":"diary","place":"Catterick","subject_id":"59539e059d936f003e003979","time":"0500PM","type":"time","votes":{},"x":17,"y":39},{"compare":"4MAR1919","coords":[0.0,0.0],"count":5,"date":"4 Mar 1919","datetime":"1919-03-04T00:00:00.000Z","group":"GWD00000r0","hit_rate":0.2,"id":"597b2e88909f05000400000c","label":"4 Mar 1919","page":"AWD0003rq1","page_number":2,"page_order":12,"page_type":"diary","place":"Catterick","subject_id":"59539e059d936f003e003979","time":"","type":"diaryDate","votes":{"day":["4"],"month":["Mar"],"year":["1919"]},"x":6,"y":43},{"compare":"0245AM","coords":[0.0,0.0],"count":3,"date":"4 Mar 1919","datetime":"1919-03-04T02:45:00.000Z","group":"GWD00000r0","hit_rate":0.6,"id":"597b2e88909f05000400000d","label":"0245AM","page":"AWD0003rq1","page_number":2,"page_order":13,"page_type":"diary","place":"Catterick","subject_id":"59539e059d936f003e003979","time":"0245AM","type":"time","votes":{},"x":18,"y":44},{"compare":"0330AM","coords":[0.0,0.0],"count":3,"date":"4 Mar 1919","datetime":"1919-03-04T03:30:00.000Z","group":"GWD00000r0","hit_rate":0.6,"id":"597b2e88909f050004000010","label":"0330AM","page":"AWD0003rq1","page_number":2,"page_order":16,"page_type":"diary","place":"Catterick","subject_id":"59539e059d936f003e003979","time":"0330AM","type":"time","votes":{},"x":17,"y":48},{"compare":"PARADES","coords":[0.0,0.0],"count":2,"date":"4 Mar 1919","datetime":"1919-03-04T03:30:00.000Z","group":"GWD00000r0","hit_rate":0.4,"id":"597b2e88909f050004000011","label":"parades","page":"AWD0003rq1","page_number":2,"page_order":17,"page_type":"diary","place":"Catterick","subject_id":"59539e059d936f003e003979","time":"0330AM","type":"domestic","votes":{},"x":27,"y":50},{"compare":"0430AM","coords":[0.0,0.0],"count":4,"date":"4 Mar 1919","datetime":"1919-03-04T04:30:00.000Z","group":"GWD00000r0","hit_rate":0.8,"id":"597b2e88909f050004000017","label":"0430AM","page":"AWD0003rq1","page_number":2,"page_order":23,"page_type":"diary","place":"Catterick","subject_id":"59539e059d936f003e003979","time":"0430AM","type":"time","votes":{},"x":17,"y":52},{"compare":"OFFICER40OTHER744","coords":[0.0,0.0],"count":2,"date":"4 Mar 1919","datetime":"1919-03-04T04:30:00.000Z","group":"GWD00000r0","hit_rate":0.4,"id":"597b2e88909f050004000019","label":"officer: 40, other: 744","page":"AWD0003rq1","page_number":2,"page_order":25,"page_type":"diary","place":"Catterick","subject_id":"59539e059d936f003e003979","time":"0430AM","type":"strength","votes":{},"x":57,"y":55},{"compare":"5MAR1919","coords":[0.0,0.0],"count":5,"date":"5 Mar 1919","datetime":"1919-03-05T00:00:00.000Z","group":"GWD00000r0","hit_rate":0.2,"id":"597b2e88909f05000400001a","label":"5 Mar 1919","page":"AWD0003rq1","page_number":2,"page_order":26,"page_type":"diary","place":"Catterick","subject_id":"59539e059d936f003e003979","time":"","type":"diaryDate","votes":{"day":["5"],"month":["Mar"],"year":["1919"]},"x":6,"y":59},{"compare":"1100AM","coords":[0.0,0.0],"count":2,"date":"5 Mar 1919","datetime":"1919-03-05T11:00:00.000Z","group":"GWD00000r0","hit_rate":0.4,"id":"597b2e88909f05000400001b","label":"1100AM","page":"AWD0003rq1","page_number":2,"page_order":27,"page_type":"diary","place":"Catterick","subject_id":"59539e059d936f003e003979","time":"1100AM","type":"time","votes":{},"x":18,"y":60},{"compare":"MOVEMENT","coords":[0.0,0.0],"count":2,"date":"5 Mar 1919","datetime":"1919-03-05T11:00:00.000Z","group":"GWD00000r0","hit_rate":0.4,"id":"597b2e88909f05000400001f","label":"movement","page":"AWD0003rq1","page_number":2,"page_order":31,"page_type":"diary","place":"Catterick","subject_id":"59539e059d936f003e003979","time":"1100AM","type":"activity","votes":{},"x":64,"y":61},{"compare":"0300PM","coords":[0.0,0.0],"count":4,"date":"5 Mar 1919","datetime":"1919-03-05T15:00:00.000Z","group":"GWD00000r0","hit_rate":0.6,"id":"597b2e88909f050004000021","label":"0300PM","page":"AWD0003rq1","page_number":2,"page_order":33,"page_type":"diary","place":"Catterick","subject_id":"59539e059d936f003e003979","time":"0300PM","type":"time","votes":{},"x":17,"y":64},{"compare":"DUNKIRK","coords":[0.97929,51.29169],"count":3,"date":"5 Mar 1919","datetime":"1919-03-05T15:00:00.000Z","group":"GWD00000r0","hit_rate":0.6,"id":"597b2e88909f050004000024","label":"Dunkirk","page":"AWD0003rq1","page_number":2,"page_order":36,"page_type":"diary","place":"Dunkirk","subject_id":"59539e059d936f003e003979","time":"0300PM","type":"place","votes":{"place":["Dunkirk"],"location":["true"],"name":["Dunkirk"],"lat":["51.29169"],"long":["0.97929"],"id":["2650712"]},"x":26,"y":65},{"compare":"6MAR1915","coords":[0.97929,51.29169],"count":4,"date":"6 Mar 1919","datetime":"1919-03-06T00:00:00.000Z","group":"GWD00000r0","hit_rate":0.8,"id":"597b2e88909f050004000025","label":"6 Mar 1919","page":"AWD0003rq1","page_number":2,"page_order":37,"page_type":"diary","place":"Dunkirk","subject_id":"59539e059d936f003e003979","time":"","type":"diaryDate","votes":{"day":["6"],"month":["Mar"],"year":["1919"]},"x":6,"y":69},{"compare":"1200PM","coords":[0.97929,51.29169],"count":3,"date":"6 Mar 1919","datetime":"1919-03-06T12:00:00.000Z","group":"GWD00000r0","hit_rate":0.6,"id":"597b2e88909f050004000026","label":"1200PM","page":"AWD0003rq1","page_number":2,"page_order":38,"page_type":"diary","place":"Dunkirk","subject_id":"59539e059d936f003e003979","time":"1200PM","type":"time","votes":{},"x":17,"y":69},{"compare":"COLOGNE","coords":[0.9775,43.72214],"count":2,"date":"6 Mar 1919","datetime":"1919-03-06T12:00:00.000Z","group":"GWD00000r0","hit_rate":0.4,"id":"597b2e89909f05000400002a","label":"Cologne","page":"AWD0003rq1","page_number":2,"page_order":42,"page_type":"diary","place":"Cologne","subject_id":"59539e059d936f003e003979","time":"1200PM","type":"place","votes":{"place":["Cologne"],"location":["true"],"name":["Cologne"],"lat":["43.72214"],"long":["0.9775"],"id":["3024280"]},"x":30,"y":70},{"compare":"7MAR1919","coords":[0.9775,43.72214],"count":4,"date":"7 Mar 1919","datetime":"1919-03-07T00:00:00.000Z","group":"GWD00000r0","hit_rate":0.8,"id":"597b2e89909f05000400002b","label":"7 Mar 1919","page":"AWD0003rq1","page_number":2,"page_order":43,"page_type":"diary","place":"Cologne","subject_id":"59539e059d936f003e003979","time":"","type":"diaryDate","votes":{"day":["7"],"month":["Mar"],"year":["1919"]},"x":6,"y":72},{"compare":"8MAR1919","coords":[0.9775,43.72214],"count":5,"date":"8 Mar 1919","datetime":"1919-03-08T00:00:00.000Z","group":"GWD00000r0","hit_rate":1.0,"id":"597b2e89909f05000400002d","label":"8 Mar 1919","page":"AWD0003rq1","page_number":2,"page_order":45,"page_type":"diary","place":"Cologne","subject_id":"59539e059d936f003e003979","time":"","type":"diaryDate","votes":{"day":["8"],"month":["Mar"],"year":["1919"]},"x":6,"y":77},{"compare":"COLOGNE","coords":[0.9775,43.72214],"count":6,"date":"8 Mar 1919","datetime":"1919-03-08T00:00:00.000Z","group":"GWD00000r0","hit_rate":1.2,"id":"597b2e89909f05000400002e","label":"Cologne","page":"AWD0003rq1","page_number":2,"page_order":46,"page_type":"diary","place":"Cologne","subject_id":"59539e059d936f003e003979","time":"","type":"place","votes":{"place":["Cologne"],"location":["true"],"name":["Cologne"],"lat":["43.72214"],"long":["0.9775"],"id":["3024280"]},"x":12,"y":77},{"compare":"0930AM","coords":[0.9775,43.72214],"count":3,"date":"8 Mar 1919","datetime":"1919-03-08T09:30:00.000Z","group":"GWD00000r0","hit_rate":0.6,"id":"597b2e89909f05000400002f","label":"0930AM","page":"AWD0003rq1","page_number":2,"page_order":47,"page_type":"diary","place":"Cologne","subject_id":"59539e059d936f003e003979","time":"0930AM","type":"time","votes":{},"x":18,"y":78},{"compare":"9MAR1919","coords":[0.9775,43.72214],"count":4,"date":"9 Mar 1919","datetime":"1919-03-09T00:00:00.000Z","group":"GWD00000r0","hit_rate":0.8,"id":"597b2e89909f050004000031","label":"9 Mar 1919","page":"AWD0003rq1","page_number":2,"page_order":49,"page_type":"diary","place":"Cologne","subject_id":"59539e059d936f003e003979","time":"","type":"diaryDate","votes":{"day":["9"],"month":["Mar"],"year":["1919"]},"x":6,"y":81},{"compare":"HYGIENE","coords":[0.9775,43.72214],"count":2,"date":"9 Mar 1919","datetime":"1919-03-09T00:00:00.000Z","group":"GWD00000r0","hit_rate":0.4,"id":"597b2e89909f050004000032","label":"hygiene","page":"AWD0003rq1","page_number":2,"page_order":50,"page_type":"diary","place":"Cologne","subject_id":"59539e059d936f003e003979","time":"","type":"domestic","votes":{},"x":28,"y":81},{"compare":"10MAR1919","coords":[0.9775,43.72214],"count":4,"date":"10 Mar 1919","datetime":"1919-03-10T00:00:00.000Z","group":"GWD00000r0","hit_rate":0.8,"id":"597b2e89909f050004000033","label":"10 Mar 1919","page":"AWD0003rq1","page_number":2,"page_order":51,"page_type":"diary","place":"Cologne","subject_id":"59539e059d936f003e003979","time":"","type":"diaryDate","votes":{"day":["10"],"month":["Mar"],"year":["1919"]},"x":6,"y":85},{"compare":"1000AM","coords":[0.9775,43.72214],"count":3,"date":"10 Mar 1919","datetime":"1919-03-10T10:00:00.000Z","group":"GWD00000r0","hit_rate":0.6,"id":"597b2e89909f050004000034","label":"1000AM","page":"AWD0003rq1","page_number":2,"page_order":52,"page_type":"diary","place":"Cologne","subject_id":"59539e059d936f003e003979","time":"1000AM","type":"time","votes":{},"x":18,"y":86},{"compare":"11MAR1919","coords":[0.9775,43.72214],"count":4,"date":"11 Mar 1919","datetime":"1919-03-11T00:00:00.000Z","group":"GWD00000r0","hit_rate":0.8,"id":"597b2e89909f050004000036","label":"11 Mar 1919","page":"AWD0003rq1","page_number":2,"page_order":54,"page_type":"diary","place":"Cologne","subject_id":"59539e059d936f003e003979","time":"","type":"diaryDate","votes":{"day":["11"],"month":["Mar"],"year":["1919"]},"x":6,"y":89},{"compare":"0200PM","coords":[0.9775,43.72214],"count":3,"date":"11 Mar 1919","datetime":"1919-03-11T14:00:00.000Z","group":"GWD00000r0","hit_rate":0.6,"id":"597b2e89909f050004000037","label":"0200PM","page":"AWD0003rq1","page_number":2,"page_order":55,"page_type":"diary","place":"Cologne","subject_id":"59539e059d936f003e003979","time":"0200PM","type":"time","votes":{},"x":18,"y":90},{"compare":"COLOGNE","coords":[0.9775,43.72214],"count":2,"date":"11 Mar 1919","datetime":"1919-03-11T14:00:00.000Z","group":"GWD00000r0","hit_rate":0.4,"id":"597b2e89909f050004000039","label":"Cologne","page":"AWD0003rq1","page_number":2,"page_order":57,"page_type":"diary","place":"Cologne","subject_id":"59539e059d936f003e003979","time":"0200PM","type":"place","votes":{"place":["Cologne"],"location":["true"],"name":["Cologne"],"lat":["43.72214"],"long":["0.9775"],"id":["3024280"]},"x":28,"y":91},{"compare":"12MAR1919","coords":[0.9775,43.72214],"count":2,"date":"12 Mar 1919","datetime":"1919-03-12T00:00:00.000Z","group":"GWD00000r0","hit_rate":0.4,"id":"597b2e89909f05000400003b","label":"12 Mar 1919","page":"AWD0003rq0","page_number":3,"page_order":2,"page_type":"diary","place":"Cologne","subject_id":"59539e059d936f003e003973","time":"","type":"diaryDate","votes":{"day":["12"],"month":["Mar"],"year":["1919"]},"x":6,"y":27},{"compare":"COLOGNE","coords":[0.9775,43.72214],"count":3,"date":"12 Mar 1919","datetime":"1919-03-12T00:00:00.000Z","group":"GWD00000r0","hit_rate":0.6,"id":"597b2e89909f05000400003c","label":"Cologne","page":"AWD0003rq0","page_number":3,"page_order":3,"page_type":"diary","place":"Cologne","subject_id":"59539e059d936f003e003973","time":"","type":"place","votes":{"place":["Cologne"],"location":["true"],"name":["Cologne"],"lat":["43.72214"],"long":["0.9775"],"id":["3024280"]},"x":7,"y":27},{"compare":"13MAR1919","coords":[0.9775,43.72214],"count":2,"date":"13 Mar 1919","datetime":"1919-03-13T00:00:00.000Z","group":"GWD00000r0","hit_rate":0.4,"id":"597b2e89909f05000400003e","label":"13 Mar 1919","page":"AWD0003rq0","page_number":3,"page_order":5,"page_type":"diary","place":"Cologne","subject_id":"59539e059d936f003e003973","time":"","type":"diaryDate","votes":{"day":["13"],"month":["Mar"],"year":["1919"]},"x":6,"y":31},{"compare":"14MAR1919","coords":[0.9775,43.72214],"count":2,"date":"14 Mar 1919","datetime":"1919-03-14T00:00:00.000Z","group":"GWD00000r0","hit_rate":0.4,"id":"597b2e89909f05000400003f","label":"14 Mar 1919","page":"AWD0003rq0","page_number":3,"page_order":6,"page_type":"diary","place":"Cologne","subject_id":"59539e059d936f003e003973","time":"","type":"diaryDate","votes":{"day":["14"],"month":["Mar"],"year":["1919"]},"x":6,"y":35},{"compare":"15MAR1919","coords":[0.9775,43.72214],"count":2,"date":"15 Mar 1919","datetime":"1919-03-15T00:00:00.000Z","group":"GWD00000r0","hit_rate":0.4,"id":"597b2e89909f050004000043","label":"15 Mar 1919","page":"AWD0003rq0","page_number":3,"page_order":10,"page_type":"diary","place":"Cologne","subject_id":"59539e059d936f003e003973","time":"","type":"diaryDate","votes":{"day":["15"],"month":["Mar"],"year":["1919"]},"x":6,"y":39},{"compare":"16MAR1919","coords":[0.9775,43.72214],"count":3,"date":"16 Mar 1919","datetime":"1919-03-16T00:00:00.000Z","group":"GWD00000r0","hit_rate":0.6,"id":"597b2e89909f050004000044","label":"16 Mar 1919","page":"AWD0003rq0","page_number":3,"page_order":11,"page_type":"diary","place":"Cologne","subject_id":"59539e059d936f003e003973","time":"","type":"diaryDate","votes":{"day":["16"],"month":["Mar"],"year":["1919"]},"x":6,"y":43},{"compare":"0940AM","coords":[0.9775,43.72214],"count":3,"date":"16 Mar 1919","datetime":"1919-03-16T09:40:00.000Z","group":"GWD00000r0","hit_rate":0.6,"id":"597b2e89909f050004000045","label":"0940AM","page":"AWD0003rq0","page_number":3,"page_order":12,"page_type":"diary","place":"Cologne","subject_id":"59539e059d936f003e003973","time":"0940AM","type":"time","votes":{},"x":17,"y":43},{"compare":"PARADES","coords":[0.9775,43.72214],"count":4,"date":"16 Mar 1919","datetime":"1919-03-16T09:40:00.000Z","group":"GWD00000r0","hit_rate":0.8,"id":"597b2e89909f050004000046","label":"parades","page":"AWD0003rq0","page_number":3,"page_order":13,"page_type":"diary","place":"Cologne","subject_id":"59539e059d936f003e003973","time":"0940AM","type":"domestic","votes":{},"x":26,"y":44},{"compare":"17MAR1919","coords":[0.9775,43.72214],"count":2,"date":"17 Mar 1919","datetime":"1919-03-17T00:00:00.000Z","group":"GWD00000r0","hit_rate":0.4,"id":"597b2e89909f050004000049","label":"17 Mar 1919","page":"AWD0003rq0","page_number":3,"page_order":16,"page_type":"diary","place":"Cologne","subject_id":"59539e059d936f003e003973","time":"","type":"diaryDate","votes":{"day":["17"],"month":["Mar"],"year":["1919"]},"x":6,"y":47},{"compare":"18MAR1919","coords":[0.9775,43.72214],"count":2,"date":"18 Mar 1919","datetime":"1919-03-18T00:00:00.000Z","group":"GWD00000r0","hit_rate":0.4,"id":"597b2e89909f05000400004a","label":"18 Mar 1919","page":"AWD0003rq0","page_number":3,"page_order":17,"page_type":"diary","place":"Cologne","subject_id":"59539e059d936f003e003973","time":"","type":"diaryDate","votes":{"day":["18"],"month":["Mar"],"year":["1919"]},"x":6,"y":51},{"compare":"20MAR1919","coords":[0.9775,43.72214],"count":2,"date":"20 Mar 1919","datetime":"1919-03-20T00:00:00.000Z","group":"GWD00000r0","hit_rate":0.4,"id":"597b2e89909f05000400004c","label":"20 Mar 1919","page":"AWD0003rq0","page_number":3,"page_order":19,"page_type":"diary","place":"Cologne","subject_id":"59539e059d936f003e003973","time":"","type":"diaryDate","votes":{"day":["20"],"month":["Mar"],"year":["1919"]},"x":6,"y":54},{"compare":"0200PM","coords":[0.9775,43.72214],"count":2,"date":"20 Mar 1919","datetime":"1919-03-20T14:00:00.000Z","group":"GWD00000r0","hit_rate":0.4,"id":"597b2e89909f05000400004d","label":"0200PM","page":"AWD0003rq0","page_number":3,"page_order":20,"page_type":"diary","place":"Cologne","subject_id":"59539e059d936f003e003973","time":"0200PM","type":"time","votes":{},"x":17,"y":55},{"compare":"COLOGNE","coords":[0.9775,43.72214],"count":2,"date":"20 Mar 1919","datetime":"1919-03-20T14:00:00.000Z","group":"GWD00000r0","hit_rate":0.4,"id":"597b2e89909f05000400004e","label":"Cologne","page":"AWD0003rq0","page_number":3,"page_order":21,"page_type":"diary","place":"Cologne","subject_id":"59539e059d936f003e003973","time":"0200PM","type":"place","votes":{"place":["Cologne"],"location":["true"],"name":["","Cologne"],"lat":["","43.72214"],"long":["","0.9775"],"id":["","3024280"]},"x":41,"y":55},{"compare":"21MAR1919","coords":[0.9775,43.72214],"count":2,"date":"21 Mar 1919","datetime":"1919-03-21T00:00:00.000Z","group":"GWD00000r0","hit_rate":0.4,"id":"597b2e89909f05000400004f","label":"21 Mar 1919","page":"AWD0003rq0","page_number":3,"page_order":22,"page_type":"diary","place":"Cologne","subject_id":"59539e059d936f003e003973","time":"","type":"diaryDate","votes":{"day":["21"],"month":["Mar"],"year":["1919"]},"x":6,"y":57},{"compare":"52DLI","coords":[0.9775,43.72214],"count":2,"date":"21 Mar 1919","datetime":"1919-03-21T00:00:00.000Z","group":"GWD00000r0","hit_rate":0.4,"id":"597b2e89909f050004000050","label":"20 DLI, 52 DLI","page":"AWD0003rq0","page_number":3,"page_order":23,"page_type":"diary","place":"Cologne","subject_id":"59539e059d936f003e003973","time":"","type":"unit","votes":{"name":["20 DLI","52 DLI"],"context":["relieved_by","relieved"]},"x":26,"y":57},{"compare":"0300PM","coords":[0.9775,43.72214],"count":2,"date":"21 Mar 1919","datetime":"1919-03-21T15:00:00.000Z","group":"GWD00000r0","hit_rate":0.4,"id":"597b2e89909f050004000057","label":"0300PM","page":"AWD0003rq0","page_number":3,"page_order":30,"page_type":"diary","place":"Cologne","subject_id":"59539e059d936f003e003973","time":"0300PM","type":"time","votes":{},"x":18,"y":64},{"compare":"0235AM","coords":[0.9775,43.72214],"count":2,"date":"21 Mar 1919","datetime":"1919-03-21T02:35:00.000Z","group":"GWD00000r0","hit_rate":0.4,"id":"597b2e89909f050004000058","label":"0235AM","page":"AWD0003rq0","page_number":3,"page_order":31,"page_type":"diary","place":"Cologne","subject_id":"59539e059d936f003e003973","time":"0235AM","type":"time","votes":{},"x":52,"y":64},{"compare":"27MAR1919","coords":[0.9775,43.72214],"count":2,"date":"27 Mar 1919","datetime":"1919-03-27T00:00:00.000Z","group":"GWD00000r0","hit_rate":0.4,"id":"597b2e89909f05000400005a","label":"27 Mar 1919","page":"AWD0003rq0","page_number":3,"page_order":33,"page_type":"diary","place":"Cologne","subject_id":"59539e059d936f003e003973","time":"","type":"diaryDate","votes":{"day":["27"],"month":["Mar"],"year":["1919"]},"x":6,"y":67},{"compare":"28MAR1919","coords":[0.9775,43.72214],"count":2,"date":"28 Mar 1919","datetime":"1919-03-28T00:00:00.000Z","group":"GWD00000r0","hit_rate":0.4,"id":"597b2e89909f05000400005b","label":"28 Mar 1919","page":"AWD0003rq0","page_number":3,"page_order":34,"page_type":"diary","place":"Cologne","subject_id":"59539e059d936f003e003973","time":"","type":"diaryDate","votes":{"day":["28"],"month":["Mar"],"year":["1919"]},"x":6,"y":69},{"compare":"29MAR1919","coords":[0.9775,43.72214],"count":2,"date":"29 Mar 1919","datetime":"1919-03-29T00:00:00.000Z","group":"GWD00000r0","hit_rate":0.4,"id":"597b2e89909f05000400005c","label":"29 Mar 1919","page":"AWD0003rq0","page_number":3,"page_order":35,"page_type":"diary","place":"Cologne","subject_id":"59539e059d936f003e003973","time":"","type":"diaryDate","votes":{"day":["29"],"month":["Mar"],"year":["1919"]},"x":6,"y":72},{"compare":"0200PM","coords":[0.9775,43.72214],"count":2,"date":"29 Mar 1919","datetime":"1919-03-29T14:00:00.000Z","group":"GWD00000r0","hit_rate":0.4,"id":"597b2e89909f05000400005e","label":"0200PM","page":"AWD0003rq0","page_number":3,"page_order":37,"page_type":"diary","place":"Cologne","subject_id":"59539e059d936f003e003973","time":"0200PM","type":"time","votes":{},"x":17,"y":73},{"compare":"30MAR1919","coords":[0.9775,43.72214],"count":2,"date":"30 Mar 1919","datetime":"1919-03-30T00:00:00.000Z","group":"GWD00000r0","hit_rate":0.4,"id":"597b2e89909f050004000060","label":"30 Mar 1919","page":"AWD0003rq0","page_number":3,"page_order":39,"page_type":"diary","place":"Cologne","subject_id":"59539e059d936f003e003973","time":"","type":"diaryDate","votes":{"day":["30"],"month":["Mar"],"year":["1919"]},"x":6,"y":75},{"compare":"31MAR1919","coords":[0.9775,43.72214],"count":2,"date":"31 Mar 1919","datetime":"1919-03-31T00:00:00.000Z","group":"GWD00000r0","hit_rate":0.4,"id":"597b2e89909f050004000061","label":"31 Mar 1919","page":"AWD0003rq0","page_number":3,"page_order":40,"page_type":"diary","place":"Cologne","subject_id":"59539e059d936f003e003973","time":"","type":"diaryDate","votes":{"day":["31"],"month":["Mar"],"year":["1919"]},"x":6,"y":77},{"compare":"1APR1919","coords":[0.9775,43.72214],"count":5,"date":"1 Apr 1919","datetime":"1919-04-01T00:00:00.000Z","group":"GWD00000r0","hit_rate":1.0,"id":"597b2e8a909f050004000064","label":"1 Apr 1919","page":"AWD0003rps","page_number":4,"page_order":2,"page_type":"diary","place":"Cologne","subject_id":"59539e059d936f003e00397d","time":"","type":"diaryDate","votes":{"day":["1"],"month":["Apr"],"year":["1919"]},"x":6,"y":26},{"compare":"COLOGNE","coords":[0.9775,43.72214],"count":4,"date":"1 Apr 1919","datetime":"1919-04-01T00:00:00.000Z","group":"GWD00000r0","hit_rate":0.8,"id":"597b2e8a909f050004000066","label":"Cologne","page":"AWD0003rps","page_number":4,"page_order":4,"page_type":"diary","place":"Cologne","subject_id":"59539e059d936f003e00397d","time":"","type":"place","votes":{"place":["Cologne"],"location":["true"],"name":["Cologne"],"lat":["43.72214"],"long":["0.9775"],"id":["3024280"]},"x":12,"y":28},{"compare":"2APR1919","coords":[0.9775,43.72214],"count":3,"date":"2 Apr 1919","datetime":"1919-04-02T00:00:00.000Z","group":"GWD00000r0","hit_rate":0.4,"id":"597b2e8a909f050004000067","label":"2 Apr 1919","page":"AWD0003rps","page_number":4,"page_order":5,"page_type":"diary","place":"Cologne","subject_id":"59539e059d936f003e00397d","time":"","type":"diaryDate","votes":{"day":["2"],"month":["Apr"],"year":["1919"]},"x":6,"y":31},{"compare":"4APR1919","coords":[0.9775,43.72214],"count":2,"date":"4 Apr 1919","datetime":"1919-04-04T00:00:00.000Z","group":"GWD00000r0","hit_rate":0.2,"id":"597b2e8a909f050004000069","label":"4 Apr 1919","page":"AWD0003rps","page_number":4,"page_order":7,"page_type":"diary","place":"Cologne","subject_id":"59539e059d936f003e00397d","time":"","type":"diaryDate","votes":{"day":["4"],"month":["Apr"],"year":["1919"]},"x":6,"y":39},{"compare":"JATUPMAN","coords":[0.9775,43.72214],"count":2,"date":"4 Apr 1919","datetime":"1919-04-04T00:00:00.000Z","group":"GWD00000r0","hit_rate":0.4,"id":"597b2e8a909f05000400006a","label":"Lieutenant Colonel JA,J H Tupman","page":"AWD0003rps","page_number":4,"page_order":8,"page_type":"diary","place":"Cologne","subject_id":"59539e059d936f003e00397d","time":"","type":"person","votes":{"first":["JA","J H"],"surname":["Tupman"],"rank":["Lieutenant Colonel"],"number":[""],"reason":["other","commander"],"unit":[""]},"x":31,"y":40},{"compare":"4APR1919","coords":[0.9775,43.72214],"count":3,"date":"4 Apr 1919","datetime":"1919-04-04T00:00:00.000Z","group":"GWD00000r0","hit_rate":0.6,"id":"597b2e8a909f05000400006d","label":"4 Apr 1919","page":"AWD0003rps","page_number":4,"page_order":11,"page_type":"diary","place":"Cologne","subject_id":"59539e059d936f003e00397d","time":"","type":"diaryDate","votes":{"day":["4"],"month":["Apr"],"year":["1919"]},"x":6,"y":47},{"compare":"5APR1919","coords":[0.9775,43.72214],"count":2,"date":"5 Apr 1919","datetime":"1919-04-05T00:00:00.000Z","group":"GWD00000r0","hit_rate":0.4,"id":"597b2e8a909f050004000073","label":"5 Apr 1919","page":"AWD0003rps","page_number":4,"page_order":17,"page_type":"diary","place":"Cologne","subject_id":"59539e059d936f003e00397d","time":"","type":"diaryDate","votes":{"day":["5"],"month":["Apr"],"year":["1919"]},"x":6,"y":56},{"compare":"JATUPMAN","coords":[0.9775,43.72214],"count":2,"date":"5 Apr 1919","datetime":"1919-04-05T00:00:00.000Z","group":"GWD00000r0","hit_rate":0.4,"id":"597b2e8a909f050004000075","label":"Lieutenant Colonel ,JA Tupman","page":"AWD0003rps","page_number":4,"page_order":19,"page_type":"diary","place":"Cologne","subject_id":"59539e059d936f003e00397d","time":"","type":"person","votes":{"first":["","JA"],"surname":["Tupman"],"rank":["Lieutenant Colonel"],"number":[""],"reason":["commander","departed_posted"],"unit":[""]},"x":32,"y":57},{"compare":"7APR1919","coords":[0.9775,43.72214],"count":3,"date":"7 Apr 1919","datetime":"1919-04-07T00:00:00.000Z","group":"GWD00000r0","hit_rate":0.6,"id":"597b2e8a909f050004000076","label":"7 Apr 1919","page":"AWD0003rps","page_number":4,"page_order":20,"page_type":"diary","place":"Cologne","subject_id":"59539e059d936f003e00397d","time":"","type":"diaryDate","votes":{"day":["7"],"month":["Apr"],"year":["1919"]},"x":6,"y":64},{"compare":"8APR1919","coords":[0.9775,43.72214],"count":3,"date":"8 Apr 1919","datetime":"1919-04-08T00:00:00.000Z","group":"GWD00000r0","hit_rate":0.6,"id":"597b2e8a909f050004000079","label":"8 Apr 1919","page":"AWD0003rps","page_number":4,"page_order":23,"page_type":"diary","place":"Cologne","subject_id":"59539e059d936f003e00397d","time":"","type":"diaryDate","votes":{"day":["8"],"month":["Apr"],"year":["1919"]},"x":6,"y":69},{"compare":"9APR1919","coords":[0.9775,43.72214],"count":2,"date":"9 Apr 1919","datetime":"1919-04-09T00:00:00.000Z","group":"GWD00000r0","hit_rate":0.4,"id":"597b2e8a909f05000400007b","label":"9 Apr 1919","page":"AWD0003rps","page_number":4,"page_order":25,"page_type":"diary","place":"Cologne","subject_id":"59539e059d936f003e00397d","time":"","type":"diaryDate","votes":{"day":["9"],"month":["Apr"],"year":["1919"]},"x":6,"y":75},{"compare":"12APR1919","coords":[0.9775,43.72214],"count":3,"date":"12 Apr 1919","datetime":"1919-04-12T00:00:00.000Z","group":"GWD00000r0","hit_rate":0.6,"id":"597b2e8a909f05000400007d","label":"12 Apr 1919","page":"AWD0003rps","page_number":4,"page_order":27,"page_type":"diary","place":"Cologne","subject_id":"59539e059d936f003e00397d","time":"","type":"diaryDate","votes":{"day":["12"],"month":["Apr"],"year":["1919"]},"x":6,"y":84},{"compare":"DGTULLY","coords":[0.9775,43.72214],"count":2,"date":"12 Apr 1919","datetime":"1919-04-12T00:00:00.000Z","group":"GWD00000r0","hit_rate":0.4,"id":"597b2e8a909f05000400007e","label":"Captain DG,D G Tully","page":"AWD0003rps","page_number":4,"page_order":28,"page_type":"diary","place":"Cologne","subject_id":"59539e059d936f003e00397d","time":"","type":"person","votes":{"first":["DG","D G"],"surname":["Tully"],"rank":["Captain"],"number":[""],"reason":["joined","commander"],"unit":[""]},"x":30,"y":85},{"compare":"13APR1919","coords":[0.9775,43.72214],"count":3,"date":"13 Apr 1919","datetime":"1919-04-13T00:00:00.000Z","group":"GWD00000r0","hit_rate":0.6,"id":"597b2e8a909f05000400007f","label":"13 Apr 1919","page":"AWD0003rps","page_number":4,"page_order":29,"page_type":"diary","place":"Cologne","subject_id":"59539e059d936f003e00397d","time":"","type":"diaryDate","votes":{"day":["13"],"month":["Apr"],"year":["1919"]},"x":6,"y":88},{"compare":"RKHINE","coords":[0.9775,43.72214],"count":2,"date":"13 Apr 1919","datetime":"1919-04-13T00:00:00.000Z","group":"GWD00000r0","hit_rate":0.4,"id":"597b2e8a909f050004000080","label":"Captain FRK,R K Hine","page":"AWD0003rps","page_number":4,"page_order":30,"page_type":"diary","place":"Cologne","subject_id":"59539e059d936f003e00397d","time":"","type":"person","votes":{"first":["FRK","R K"],"surname":["Hine"],"rank":["Captain"],"number":[""],"reason":["other","departed_posted"],"unit":[""]},"x":31,"y":89},{"compare":"15APR1919","coords":[0.9775,43.72214],"count":5,"date":"15 Apr 1919","datetime":"1919-04-15T00:00:00.000Z","group":"GWD00000r0","hit_rate":1.0,"id":"597b2e8a909f050004000083","label":"15 Apr 1919","page":"AWD0003rpt","page_number":5,"page_order":2,"page_type":"diary","place":"Cologne","subject_id":"59539e059d936f003e003971","time":"","type":"diaryDate","votes":{"day":["15"],"month":["Apr"],"year":["1919"]},"x":6,"y":25},{"compare":"COLOGNE","coords":[0.9775,43.72214],"count":3,"date":"15 Apr 1919","datetime":"1919-04-15T00:00:00.000Z","group":"GWD00000r0","hit_rate":0.6,"id":"597b2e8a909f050004000084","label":"Cologne","page":"AWD0003rpt","page_number":5,"page_order":3,"page_type":"diary","place":"Cologne","subject_id":"59539e059d936f003e003971","time":"","type":"place","votes":{"place":["Cologne"],"location":["true"],"name":["Cologne"],"lat":["43.72214"],"long":["0.9775"],"id":["3024280"]},"x":8,"y":27},{"compare":"INSPECTIONS","coords":[0.9775,43.72214],"count":3,"date":"15 Apr 1919","datetime":"1919-04-15T00:00:00.000Z","group":"GWD00000r0","hit_rate":0.6,"id":"597b2e8a909f050004000086","label":"inspections","page":"AWD0003rpt","page_number":5,"page_order":5,"page_type":"diary","place":"Cologne","subject_id":"59539e059d936f003e003971","time":"","type":"domestic","votes":{},"x":34,"y":28},{"compare":"16APR1919","coords":[0.9775,43.72214],"count":4,"date":"16 Apr 1919","datetime":"1919-04-16T00:00:00.000Z","group":"GWD00000r0","hit_rate":0.8,"id":"597b2e8a909f050004000089","label":"16 Apr 1919","page":"AWD0003rpt","page_number":5,"page_order":8,"page_type":"diary","place":"Cologne","subject_id":"59539e059d936f003e003971","time":"","type":"diaryDate","votes":{"day":["16"],"month":["Apr"],"year":["1919"]},"x":6,"y":35},{"compare":"17APR1919","coords":[0.9775,43.72214],"count":3,"date":"17 Apr 1919","datetime":"1919-04-17T00:00:00.000Z","group":"GWD00000r0","hit_rate":0.6,"id":"597b2e8a909f05000400008c","label":"17 Apr 1919","page":"AWD0003rpt","page_number":5,"page_order":11,"page_type":"diary","place":"Cologne","subject_id":"59539e059d936f003e003971","time":"","type":"diaryDate","votes":{"day":["17"],"month":["Apr"],"year":["1919"]},"x":6,"y":43},{"compare":"18APR1919","coords":[0.9775,43.72214],"count":3,"date":"18 Apr 1919","datetime":"1919-04-18T00:00:00.000Z","group":"GWD00000r0","hit_rate":0.6,"id":"597b2e8a909f05000400008e","label":"18 Apr 1919","page":"AWD0003rpt","page_number":5,"page_order":13,"page_type":"diary","place":"Cologne","subject_id":"59539e059d936f003e003971","time":"","type":"diaryDate","votes":{"day":["18"],"month":["Apr"],"year":["1919"]},"x":6,"y":47},{"compare":"","coords":[0.9775,43.72214],"count":2,"date":"18 Apr 1919","datetime":"1919-04-18T00:00:00.000Z","group":"GWD00000r0","hit_rate":0.4,"id":"597b2e8a909f05000400008f","label":"Major,  ","page":"AWD0003rpt","page_number":5,"page_order":14,"page_type":"diary","place":"Cologne","subject_id":"59539e059d936f003e003971","time":"","type":"person","votes":{"first":[""],"surname":[""],"rank":["Major",""],"number":[""],"reason":["commander","resigned"],"unit":[""]},"x":26,"y":47},{"compare":"19APR1919","coords":[0.9775,43.72214],"count":3,"date":"19 Apr 1919","datetime":"1919-04-19T00:00:00.000Z","group":"GWD00000r0","hit_rate":0.6,"id":"597b2e8a909f050004000090","label":"19 Apr 1919","page":"AWD0003rpt","page_number":5,"page_order":15,"page_type":"diary","place":"Cologne","subject_id":"59539e059d936f003e003971","time":"","type":"diaryDate","votes":{"day":["19"],"month":["Apr"],"year":["1919"]},"x":6,"y":51},{"compare":"20APR1919","coords":[0.9775,43.72214],"count":3,"date":"20 Apr 1919","datetime":"1919-04-20T00:00:00.000Z","group":"GWD00000r0","hit_rate":0.6,"id":"597b2e8a909f050004000093","label":"20 Apr 1919","page":"AWD0003rpt","page_number":5,"page_order":18,"page_type":"diary","place":"Cologne","subject_id":"59539e059d936f003e003971","time":"","type":"diaryDate","votes":{"day":["20"],"month":["Apr"],"year":["1919"]},"x":6,"y":55},{"compare":"21APR1919","coords":[0.9775,43.72214],"count":3,"date":"21 Apr 1919","datetime":"1919-04-21T00:00:00.000Z","group":"GWD00000r0","hit_rate":0.6,"id":"597b2e8a909f050004000095","label":"21 Apr 1919","page":"AWD0003rpt","page_number":5,"page_order":20,"page_type":"diary","place":"Cologne","subject_id":"59539e059d936f003e003971","time":"","type":"diaryDate","votes":{"day":["21"],"month":["Apr"],"year":["1919"]},"x":6,"y":63},{"compare":"","coords":[0.9775,43.72214],"count":2,"date":"21 Apr 1919","datetime":"1919-04-21T00:00:00.000Z","group":"GWD00000r0","hit_rate":0.4,"id":"597b2e8a909f050004000096","label":"Officer Cadet  ","page":"AWD0003rpt","page_number":5,"page_order":21,"page_type":"diary","place":"Cologne","subject_id":"59539e059d936f003e003971","time":"","type":"person","votes":{"first":[""],"surname":[""],"rank":["Officer Cadet"],"number":[""],"reason":["joined"],"unit":[""]},"x":25,"y":65},{"compare":"22APR1919","coords":[0.9775,43.72214],"count":3,"date":"22 Apr 1919","datetime":"1919-04-22T00:00:00.000Z","group":"GWD00000r0","hit_rate":0.6,"id":"597b2e8a909f050004000097","label":"22 Apr 1919","page":"AWD0003rpt","page_number":5,"page_order":22,"page_type":"diary","place":"Cologne","subject_id":"59539e059d936f003e003971","time":"","type":"diaryDate","votes":{"day":["22"],"month":["Apr"],"year":["1919"]},"x":6,"y":71},{"compare":"23APR1919","coords":[0.9775,43.72214],"count":3,"date":"23 Apr 1919","datetime":"1919-04-23T00:00:00.000Z","group":"GWD00000r0","hit_rate":0.6,"id":"597b2e8a909f050004000099","label":"23 Apr 1919","page":"AWD0003rpt","page_number":5,"page_order":24,"page_type":"diary","place":"Cologne","subject_id":"59539e059d936f003e003971","time":"","type":"diaryDate","votes":{"day":["23"],"month":["Apr"],"year":["1919"]},"x":6,"y":76},{"compare":"24APR1919","coords":[0.9775,43.72214],"count":3,"date":"24 Apr 1919","datetime":"1919-04-24T00:00:00.000Z","group":"GWD00000r0","hit_rate":0.6,"id":"597b2e8a909f05000400009b","label":"24 Apr 1919","page":"AWD0003rpt","page_number":5,"page_order":26,"page_type":"diary","place":"Cologne","subject_id":"59539e059d936f003e003971","time":"","type":"diaryDate","votes":{"day":["24"],"month":["Apr"],"year":["1919"]},"x":6,"y":81},{"compare":"25APR1919","coords":[0.9775,43.72214],"count":4,"date":"25 Apr 1919","datetime":"1919-04-25T00:00:00.000Z","group":"GWD00000r0","hit_rate":0.8,"id":"597b2e8a909f05000400009d","label":"25 Apr 1919","page":"AWD0003rpt","page_number":5,"page_order":28,"page_type":"diary","place":"Cologne","subject_id":"59539e059d936f003e003971","time":"","type":"diaryDate","votes":{"day":["25"],"month":["Apr"],"year":["1919"]},"x":6,"y":85},{"compare":"26APR1919","coords":[0.9775,43.72214],"count":3,"date":"26 Apr 1919","datetime":"1919-04-26T00:00:00.000Z","group":"GWD00000r0","hit_rate":0.6,"id":"597b2e8a909f0500040000a1","label":"26 Apr 1919","page":"AWD0003rq2","page_number":6,"page_order":3,"page_type":"diary","place":"Cologne","subject_id":"59539e059d936f003e00397b","time":"","type":"diaryDate","votes":{"day":["26"],"month":["Apr"],"year":["1919"]},"x":6,"y":26},{"compare":"COLOGNE","coords":[0.9775,43.72214],"count":3,"date":"26 Apr 1919","datetime":"1919-04-26T00:00:00.000Z","group":"GWD00000r0","hit_rate":0.6,"id":"597b2e8a909f0500040000a2","label":"Cologne","page":"AWD0003rq2","page_number":6,"page_order":4,"page_type":"diary","place":"Cologne","subject_id":"59539e059d936f003e00397b","time":"","type":"place","votes":{"place":["Cologne"],"location":["true"],"name":["Cologne"],"lat":["43.72214"],"long":["0.9775"],"id":["3024280"]},"x":7,"y":28},{"compare":"27APR1919","coords":[0.9775,43.72214],"count":2,"date":"27 Apr 1919","datetime":"1919-04-27T00:00:00.000Z","group":"GWD00000r0","hit_rate":0.4,"id":"597b2e8b909f0500040000a5","label":"27 Apr 1919","page":"AWD0003rq2","page_number":6,"page_order":7,"page_type":"diary","place":"Cologne","subject_id":"59539e059d936f003e00397b","time":"","type":"diaryDate","votes":{"day":["27"],"month":["Apr"],"year":["1919"]},"x":6,"y":40},{"compare":"28APR1919","coords":[0.9775,43.72214],"count":2,"date":"28 Apr 1919","datetime":"1919-04-28T00:00:00.000Z","group":"GWD00000r0","hit_rate":0.4,"id":"597b2e8b909f0500040000a6","label":"28 Apr 1919","page":"AWD0003rq2","page_number":6,"page_order":8,"page_type":"diary","place":"Cologne","subject_id":"59539e059d936f003e00397b","time":"","type":"diaryDate","votes":{"day":["28"],"month":["Apr"],"year":["1919"]},"x":6,"y":47},{"compare":"29APR1919","coords":[0.9775,43.72214],"count":3,"date":"29 Apr 1919","datetime":"1919-04-29T00:00:00.000Z","group":"GWD00000r0","hit_rate":0.6,"id":"597b2e8b909f0500040000a8","label":"29 Apr 1919","page":"AWD0003rq2","page_number":6,"page_order":10,"page_type":"diary","place":"Cologne","subject_id":"59539e059d936f003e00397b","time":"","type":"diaryDate","votes":{"day":["29"],"month":["Apr"],"year":["1919"]},"x":6,"y":55},{"compare":"PARADES","coords":[0.9775,43.72214],"count":2,"date":"29 Apr 1919","datetime":"1919-04-29T00:00:00.000Z","group":"GWD00000r0","hit_rate":0.4,"id":"597b2e8b909f0500040000a9","label":"parades","page":"AWD0003rq2","page_number":6,"page_order":11,"page_type":"diary","place":"Cologne","subject_id":"59539e059d936f003e00397b","time":"","type":"domestic","votes":{},"x":69,"y":55},{"compare":"30APR1919","coords":[0.9775,43.72214],"count":3,"date":"30 Apr 1919","datetime":"1919-04-30T00:00:00.000Z","group":"GWD00000r0","hit_rate":0.6,"id":"597b2e8b909f0500040000ac","label":"30 Apr 1919","page":"AWD0003rq2","page_number":6,"page_order":14,"page_type":"diary","place":"Cologne","subject_id":"59539e059d936f003e00397b","time":"","type":"diaryDate","votes":{"day":["30"],"month":["Apr"],"year":["1919"]},"x":6,"y":70},{"compare":"1JUN1919","coords":[0.9775,43.72214],"count":4,"date":"1 May 1919","datetime":"1919-05-01T00:00:00.000Z","group":"GWD00000r0","hit_rate":0.8,"id":"597b2e8b909f0500040000ad","label":"1 May 1919","page":"AWD0003rpu","page_number":8,"page_order":1,"page_type":"diary","place":"Cologne","subject_id":"59539e059d936f003e00397f","time":"","type":"diaryDate","votes":{"day":["1"],"month":["May"],"year":["1919"]},"x":6,"y":24},{"compare":"COLOGNE","coords":[5.14209,48.20005],"count":3,"date":"1 May 1919","datetime":"1919-05-01T00:00:00.000Z","group":"GWD00000r0","hit_rate":0.6,"id":"597b2e8b909f0500040000b1","label":"Bologne","page":"AWD0003rpu","page_number":8,"page_order":5,"page_type":"diary","place":"Bologne","subject_id":"59539e059d936f003e00397f","time":"","type":"place","votes":{"place":["Bologne"],"location":["true"],"name":["Bologne"],"lat":["48.20005"],"long":["5.14209"],"id":["3031862"]},"x":8,"y":28},{"compare":"3JUN1919","coords":[5.14209,48.20005],"count":2,"date":"3 May,Jun 1919","group":"GWD00000r0","hit_rate":0.4,"id":"597b2e8b909f0500040000b3","label":"3 May,Jun 1919","page":"AWD0003rpu","page_number":8,"page_order":7,"page_type":"diary","place":"Bologne","subject_id":"59539e059d936f003e00397f","time":"","type":"diaryDate","votes":{"day":["3"],"month":["May","Jun"],"year":["1919"]},"x":6,"y":31},{"compare":"3MAY1919","coords":[5.14209,48.20005],"count":2,"date":"3 May 1919","datetime":"1919-05-03T00:00:00.000Z","group":"GWD00000r0","hit_rate":0.2,"id":"597b2e8b909f0500040000b4","label":"3 May 1919","page":"AWD0003rpu","page_number":8,"page_order":8,"page_type":"diary","place":"Bologne","subject_id":"59539e059d936f003e00397f","time":"","type":"diaryDate","votes":{"day":["3"],"month":["May"],"year":["1919"]},"x":6,"y":31},{"compare":"INSPECTIONS","coords":[5.14209,48.20005],"count":4,"date":"3 May 1919","datetime":"1919-05-03T00:00:00.000Z","group":"GWD00000r0","hit_rate":0.8,"id":"597b2e8b909f0500040000b6","label":"inspections","page":"AWD0003rpu","page_number":8,"page_order":10,"page_type":"diary","place":"Bologne","subject_id":"59539e059d936f003e00397f","time":"","type":"domestic","votes":{},"x":43,"y":32},{"compare":"4JUN1919","coords":[5.14209,48.20005],"count":2,"date":"4 May,Jun 1919","group":"GWD00000r0","hit_rate":0.4,"id":"597b2e8b909f0500040000b8","label":"4 May,Jun 1919","page":"AWD0003rpu","page_number":8,"page_order":12,"page_type":"diary","place":"Bologne","subject_id":"59539e059d936f003e00397f","time":"","type":"diaryDate","votes":{"day":["4"],"month":["May","Jun"],"year":["1919"]},"x":6,"y":35},{"compare":"5JUN1919","coords":[5.14209,48.20005],"count":2,"date":"5 May,Jun 1919","group":"GWD00000r0","hit_rate":0.4,"id":"597b2e8b909f0500040000bb","label":"5 May,Jun 1919","page":"AWD0003rpu","page_number":8,"page_order":15,"page_type":"diary","place":"Bologne","subject_id":"59539e059d936f003e00397f","time":"","type":"diaryDate","votes":{"day":["5"],"month":["May","Jun"],"year":["1919"]},"x":6,"y":39},{"compare":"7JUN1919","coords":[5.14209,48.20005],"count":2,"date":"7 May,Jun 1919","group":"GWD00000r0","hit_rate":0.4,"id":"597b2e8b909f0500040000bd","label":"7 May,Jun 1919","page":"AWD0003rpu","page_number":8,"page_order":17,"page_type":"diary","place":"Bologne","subject_id":"59539e059d936f003e00397f","time":"","type":"diaryDate","votes":{"day":["7"],"month":["May","Jun"],"year":["1919"]},"x":6,"y":43},{"compare":"OTHER","coords":[5.14209,48.20005],"count":2,"date":"7 May,Jun 1919","group":"GWD00000r0","hit_rate":0.2,"id":"597b2e8b909f0500040000c0","label":"other","page":"AWD0003rpu","page_number":8,"page_order":20,"page_type":"diary","place":"Bologne","subject_id":"59539e059d936f003e00397f","time":"","type":"domestic","votes":{},"x":25,"y":46},{"compare":"8JUN1919","coords":[5.14209,48.20005],"count":2,"date":"8 May,Jun 1919","group":"GWD00000r0","hit_rate":0.4,"id":"597b2e8b909f0500040000c1","label":"8 May,Jun 1919","page":"AWD0003rpu","page_number":8,"page_order":21,"page_type":"diary","place":"Bologne","subject_id":"59539e059d936f003e00397f","time":"","type":"diaryDate","votes":{"day":["8"],"month":["May","Jun"],"year":["1919"]},"x":6,"y":52},{"compare":"INSPECTIONS","coords":[5.14209,48.20005],"count":2,"date":"8 May,Jun 1919","group":"GWD00000r0","hit_rate":0.4,"id":"597b2e8b909f0500040000c4","label":"inspections","page":"AWD0003rpu","page_number":8,"page_order":24,"page_type":"diary","place":"Bologne","subject_id":"59539e059d936f003e00397f","time":"","type":"domestic","votes":{},"x":41,"y":53},{"compare":"9JUN1919","coords":[5.14209,48.20005],"count":2,"date":"9 May,Jun 1919","group":"GWD00000r0","hit_rate":0.4,"id":"597b2e8b909f0500040000c6","label":"9 May,Jun 1919","page":"AWD0003rpu","page_number":8,"page_order":26,"page_type":"diary","place":"Bologne","subject_id":"59539e059d936f003e00397f","time":"","type":"diaryDate","votes":{"day":["9"],"month":["May","Jun"],"year":["1919"]},"x":6,"y":56},{"compare":"52DLI","coords":[5.14209,48.20005],"count":2,"date":"9 May,Jun 1919","group":"GWD00000r0","hit_rate":0.4,"id":"597b2e8b909f0500040000c8","label":"52 DLI, 52nd DLT","page":"AWD0003rpu","page_number":8,"page_order":28,"page_type":"diary","place":"Bologne","subject_id":"59539e059d936f003e00397f","time":"","type":"unit","votes":{"name":["52 DLI","52nd DLT"],"context":["relieved"]},"x":42,"y":57},{"compare":"10MAY1919","coords":[5.14209,48.20005],"count":3,"date":"10 May 1919","datetime":"1919-05-10T00:00:00.000Z","group":"GWD00000r0","hit_rate":0.6,"id":"597b2e8b909f0500040000c9","label":"10 May 1919","page":"AWD0003rpu","page_number":8,"page_order":29,"page_type":"diary","place":"Bologne","subject_id":"59539e059d936f003e00397f","time":"","type":"diaryDate","votes":{"day":["10"],"month":["May"],"year":["1919"]},"x":6,"y":60},{"compare":"KIRTON","coords":[5.14209,48.20005],"count":2,"date":"10 May 1919","datetime":"1919-05-10T00:00:00.000Z","group":"GWD00000r0","hit_rate":0.4,"id":"597b2e8b909f0500040000ce","label":"Major  Kirton","page":"AWD0003rpu","page_number":8,"page_order":34,"page_type":"diary","place":"Bologne","subject_id":"59539e059d936f003e00397f","time":"","type":"person","votes":{"first":[""],"surname":["Kirton"],"rank":["Major"],"number":[""],"reason":["commander"],"unit":[""]},"x":82,"y":66},{"compare":"12JUN1919","coords":[5.14209,48.20005],"count":3,"date":"12 May 1919","datetime":"1919-05-12T00:00:00.000Z","group":"GWD00000r0","hit_rate":0.6,"id":"597b2e8b909f0500040000cf","label":"12 May 1919","page":"AWD0003rpu","page_number":8,"page_order":35,"page_type":"diary","place":"Bologne","subject_id":"59539e059d936f003e00397f","time":"","type":"diaryDate","votes":{"day":["12"],"month":["May"],"year":["1919"]},"x":6,"y":68},{"compare":"13JUN1919","coords":[5.14209,48.20005],"count":3,"date":"13 May 1919","datetime":"1919-05-13T00:00:00.000Z","group":"GWD00000r0","hit_rate":0.6,"id":"597b2e8b909f0500040000d2","label":"13 May 1919","page":"AWD0003rpu","page_number":8,"page_order":38,"page_type":"diary","place":"Bologne","subject_id":"59539e059d936f003e00397f","time":"","type":"diaryDate","votes":{"day":["13"],"month":["May"],"year":["1919"]},"x":6,"y":77},{"compare":"14JUN1919","coords":[5.14209,48.20005],"count":2,"date":"14 May,Jun 1919","group":"GWD00000r0","hit_rate":0.4,"id":"597b2e8b909f0500040000d4","label":"14 May,Jun 1919","page":"AWD0003rpu","page_number":8,"page_order":40,"page_type":"diary","place":"Bologne","subject_id":"59539e059d936f003e00397f","time":"","type":"diaryDate","votes":{"day":["14"],"month":["May","Jun"],"year":["1919"]},"x":6,"y":81},{"compare":"15MAY1919","coords":[5.14209,48.20005],"count":3,"date":"15 May 1919","datetime":"1919-05-15T00:00:00.000Z","group":"GWD00000r0","hit_rate":0.6,"id":"597b2e8b909f0500040000d7","label":"15 May 1919","page":"AWD0003rpu","page_number":8,"page_order":43,"page_type":"diary","place":"Bologne","subject_id":"59539e059d936f003e00397f","time":"","type":"diaryDate","votes":{"day":["15"],"month":["May"],"year":["1919"]},"x":6,"y":85},{"compare":"INSPECTIONS","coords":[5.14209,48.20005],"count":2,"date":"15 May 1919","datetime":"1919-05-15T00:00:00.000Z","group":"GWD00000r0","hit_rate":0.4,"id":"597b2e8b909f0500040000d9","label":"inspections","page":"AWD0003rpu","page_number":8,"page_order":45,"page_type":"diary","place":"Bologne","subject_id":"59539e059d936f003e00397f","time":"","type":"domestic","votes":{},"x":48,"y":86},{"compare":"16JUN1919","coords":[5.14209,48.20005],"count":4,"date":"16 May 1919","datetime":"1919-05-16T00:00:00.000Z","group":"GWD00000r0","hit_rate":0.8,"id":"597b2e8b909f0500040000da","label":"16 May 1919","page":"AWD0003rpu","page_number":8,"page_order":46,"page_type":"diary","place":"Bologne","subject_id":"59539e059d936f003e00397f","time":"","type":"diaryDate","votes":{"day":["16"],"month":["May"],"year":["1919"]},"x":6,"y":90},{"compare":"17MAY1919","coords":[5.14209,48.20005],"count":3,"date":"17 May 1919","datetime":"1919-05-17T00:00:00.000Z","group":"GWD00000r0","hit_rate":0.75,"id":"597b2e8b909f0500040000df","label":"17 May 1919","page":"AWD0003rpz","page_number":9,"page_order":2,"page_type":"diary","place":"Bologne","subject_id":"59539e059d936f003e00396f","time":"","type":"diaryDate","votes":{"day":["17"],"month":["May"],"year":["1919"]},"x":6,"y":24},{"compare":"BOLOGNE","coords":[5.14209,48.20005],"count":2,"date":"17 May 1919","datetime":"1919-05-17T00:00:00.000Z","group":"GWD00000r0","hit_rate":0.5,"id":"597b2e8b909f0500040000e1","label":"Cologne, Bologne","page":"AWD0003rpz","page_number":9,"page_order":4,"page_type":"diary","place":"Cologne, Bologne","subject_id":"59539e059d936f003e00396f","time":"","type":"place","votes":{"place":["Cologne","Bologne"],"location":["true"],"name":["","Bologne"],"lat":["","48.20005"],"long":["","5.14209"],"id":["","3031862"]},"x":8,"y":26},{"compare":"SPORT","coords":[5.14209,48.20005],"count":2,"date":"17 May 1919","datetime":"1919-05-17T00:00:00.000Z","group":"GWD00000r0","hit_rate":0.5,"id":"597b2e8b909f0500040000e2","label":"sport","page":"AWD0003rpz","page_number":9,"page_order":5,"page_type":"diary","place":"Cologne, Bologne","subject_id":"59539e059d936f003e00396f","time":"","type":"domestic","votes":{},"x":47,"y":27},{"compare":"MREDGARBELLINHAM","coords":[5.14209,48.20005],"count":2,"date":"17 May 1919","datetime":"1919-05-17T00:00:00.000Z","group":"GWD00000r0","hit_rate":0.5,"id":"597b2e8b909f0500040000e3","label":" Mr Edgar,Edgar Bellinham, Bellingham","page":"AWD0003rpz","page_number":9,"page_order":6,"page_type":"diary","place":"Cologne, Bologne","subject_id":"59539e059d936f003e00396f","time":"","type":"person","votes":{"first":["Mr Edgar","Edgar"],"surname":["Bellinham","Bellingham"],"rank":[""],"number":[""],"reason":["other"],"unit":[""]},"x":83,"y":27},{"compare":"1115AM","coords":[5.14209,48.20005],"count":2,"date":"17 May 1919","datetime":"1919-05-17T11:15:00.000Z","group":"GWD00000r0","hit_rate":0.5,"id":"597b2e8b909f0500040000e6","label":"1115AM","page":"AWD0003rpz","page_number":9,"page_order":9,"page_type":"diary","place":"Cologne, Bologne","subject_id":"59539e059d936f003e00396f","time":"1115AM","type":"time","votes":{},"x":50,"y":31},{"compare":"19MAY1919","coords":[5.14209,48.20005],"count":2,"date":"19 May 1919","datetime":"1919-05-19T00:00:00.000Z","group":"GWD00000r0","hit_rate":0.5,"id":"597b2e8b909f0500040000e7","label":"19 May 1919","page":"AWD0003rpz","page_number":9,"page_order":10,"page_type":"diary","place":"Cologne, Bologne","subject_id":"59539e059d936f003e00396f","time":"","type":"diaryDate","votes":{"day":["19"],"month":["May"],"year":["1919"]},"x":6,"y":34},{"compare":"20MAY1919","coords":[5.14209,48.20005],"count":3,"date":"20 May 1919","datetime":"1919-05-20T00:00:00.000Z","group":"GWD00000r0","hit_rate":0.5,"id":"597b2e8b909f0500040000ea","label":"20 May 1919","page":"AWD0003rpz","page_number":9,"page_order":13,"page_type":"diary","place":"Cologne, Bologne","subject_id":"59539e059d936f003e00396f","time":"","type":"diaryDate","votes":{"day":["20"],"month":["May"],"year":["1919"]},"x":6,"y":43},{"compare":"COLOGNE","coords":[0.0,0.0],"count":2,"date":"20 May 1919","datetime":"1919-05-20T00:00:00.000Z","group":"GWD00000r0","hit_rate":0.5,"id":"597b2e8b909f0500040000eb","label":"Cologne","page":"AWD0003rpz","page_number":9,"page_order":14,"page_type":"diary","place":"Cologne","subject_id":"59539e059d936f003e00396f","time":"","type":"place","votes":{"place":["Cologne"],"location":["true"],"name":[""],"lat":[""],"long":[""],"id":[""]},"x":7,"y":44},{"compare":"INSPECTIONS","coords":[0.0,0.0],"count":4,"date":"20 May 1919","datetime":"1919-05-20T00:00:00.000Z","group":"GWD00000r0","hit_rate":1.0,"id":"597b2e8b909f0500040000ec","label":"inspections","page":"AWD0003rpz","page_number":9,"page_order":15,"page_type":"diary","place":"Cologne","subject_id":"59539e059d936f003e00396f","time":"","type":"domestic","votes":{},"x":29,"y":44},{"compare":"22MAY1919","coords":[0.0,0.0],"count":2,"date":"22 May 1919","datetime":"1919-05-22T00:00:00.000Z","group":"GWD00000r0","hit_rate":0.25,"id":"597b2e8b909f0500040000ed","label":"22 May 1919","page":"AWD0003rpz","page_number":9,"page_order":16,"page_type":"diary","place":"Cologne","subject_id":"59539e059d936f003e00396f","time":"","type":"diaryDate","votes":{"day":["22"],"month":["May"],"year":["1919"]},"x":6,"y":47},{"compare":"BJCURLING","coords":[0.0,0.0],"count":3,"date":"22 May 1919","datetime":"1919-05-22T00:00:00.000Z","group":"GWD00000r0","hit_rate":0.25,"id":"597b2e8c909f0500040000ef","label":"Lieutenant Colonel B J,BJ,B G Curling","page":"AWD0003rpz","page_number":9,"page_order":18,"page_type":"diary","place":"Cologne","subject_id":"59539e059d936f003e00396f","time":"","type":"person","votes":{"first":["B J","BJ","B G"],"surname":["Curling"],"rank":["Lieutenant Colonel"],"number":[""],"reason":["returned_leave"],"unit":[""]},"x":66,"y":48},{"compare":"24MAY1919","coords":[0.0,0.0],"count":2,"date":"24 May 1919","datetime":"1919-05-24T00:00:00.000Z","group":"GWD00000r0","hit_rate":0.5,"id":"597b2e8c909f0500040000f0","label":"24 May 1919","page":"AWD0003rpz","page_number":9,"page_order":19,"page_type":"diary","place":"Cologne","subject_id":"59539e059d936f003e00396f","time":"","type":"diaryDate","votes":{"day":["24"],"month":["May"],"year":["1919"]},"x":6,"y":51},{"compare":"COLOGNE","coords":[0.0,0.0],"count":2,"date":"24 May 1919","datetime":"1919-05-24T00:00:00.000Z","group":"GWD00000r0","hit_rate":0.5,"id":"597b2e8c909f0500040000f1","label":"Cologne","page":"AWD0003rpz","page_number":9,"page_order":20,"page_type":"diary","place":"Cologne","subject_id":"59539e059d936f003e00396f","time":"","type":"place","votes":{"place":["Cologne"],"location":["true"],"name":[""],"lat":[""],"long":[""],"id":[""]},"x":7,"y":53},{"compare":"SPORT","coords":[0.0,0.0],"count":2,"date":"24 May 1919","datetime":"1919-05-24T00:00:00.000Z","group":"GWD00000r0","hit_rate":0.5,"id":"597b2e8c909f0500040000f3","label":"sport","page":"AWD0003rpz","page_number":9,"page_order":22,"page_type":"diary","place":"Cologne","subject_id":"59539e059d936f003e00396f","time":"","type":"domestic","votes":{},"x":48,"y":53},{"compare":"1100AM","coords":[0.0,0.0],"count":2,"date":"24 May 1919","datetime":"1919-05-24T11:00:00.000Z","group":"GWD00000r0","hit_rate":0.5,"id":"597b2e8c909f0500040000f4","label":"1100AM","page":"AWD0003rpz","page_number":9,"page_order":23,"page_type":"diary","place":"Cologne","subject_id":"59539e059d936f003e00396f","time":"1100AM","type":"time","votes":{},"x":76,"y":53},{"compare":"26MAY1919","coords":[0.0,0.0],"count":3,"date":"26 May 1919","datetime":"1919-05-26T00:00:00.000Z","group":"GWD00000r0","hit_rate":0.75,"id":"597b2e8c909f0500040000f5","label":"26 May 1919","page":"AWD0003rpz","page_number":9,"page_order":24,"page_type":"diary","place":"Cologne","subject_id":"59539e059d936f003e00396f","time":"","type":"diaryDate","votes":{"day":["26"],"month":["May"],"year":["1919"]},"x":6,"y":55},{"compare":"INSPECTIONS","coords":[0.0,0.0],"count":4,"date":"26 May 1919","datetime":"1919-05-26T00:00:00.000Z","group":"GWD00000r0","hit_rate":1.0,"id":"597b2e8c909f0500040000f6","label":"inspections","page":"AWD0003rpz","page_number":9,"page_order":25,"page_type":"diary","place":"Cologne","subject_id":"59539e059d936f003e00396f","time":"","type":"domestic","votes":{},"x":28,"y":57},{"compare":"COLOGNE","coords":[0.0,0.0],"count":2,"date":"26 May 1919","datetime":"1919-05-26T00:00:00.000Z","group":"GWD00000r0","hit_rate":0.5,"id":"597b2e8c909f0500040000f9","label":"Cologne","page":"AWD0003rpz","page_number":9,"page_order":28,"page_type":"diary","place":"Cologne","subject_id":"59539e059d936f003e00396f","time":"","type":"place","votes":{"place":["Cologne"],"location":["true"],"name":[""],"lat":[""],"long":[""],"id":[""]},"x":6,"y":60},{"compare":"27MAY1919","coords":[0.0,0.0],"count":2,"date":"27 May 1919","datetime":"1919-05-27T00:00:00.000Z","group":"GWD00000r0","hit_rate":0.25,"id":"597b2e8c909f0500040000fa","label":"27 May 1919","page":"AWD0003rpz","page_number":9,"page_order":29,"page_type":"diary","place":"Cologne","subject_id":"59539e059d936f003e00396f","time":"","type":"diaryDate","votes":{"day":["27"],"month":["May"],"year":["1919"]},"x":6,"y":60},{"compare":"REVJADOUGLAS","coords":[0.0,0.0],"count":2,"date":"27 May 1919","datetime":"1919-05-27T00:00:00.000Z","group":"GWD00000r0","hit_rate":0.5,"id":"597b2e8c909f0500040000fd","label":"other, J A,Rev JA Douglas","page":"AWD0003rpz","page_number":9,"page_order":32,"page_type":"diary","place":"Cologne","subject_id":"59539e059d936f003e00396f","time":"","type":"person","votes":{"first":["J A","Rev JA"],"surname":["Douglas"],"rank":["other",""],"number":[""],"reason":["other"],"unit":[""]},"x":64,"y":62},{"compare":"31MAY1919","coords":[0.0,0.0],"count":2,"date":"31 May 1919","datetime":"1919-05-31T00:00:00.000Z","group":"GWD00000r0","hit_rate":0.25,"id":"597b2e8c909f0500040000fe","label":"31 May 1919","page":"AWD0003rpz","page_number":9,"page_order":33,"page_type":"diary","place":"Cologne","subject_id":"59539e059d936f003e00396f","time":"","type":"diaryDate","votes":{"day":["31"],"month":["May"],"year":["1919"]},"x":6,"y":68},{"compare":"SPORT","coords":[0.0,0.0],"count":2,"date":"31 May 1919","datetime":"1919-05-31T00:00:00.000Z","group":"GWD00000r0","hit_rate":0.5,"id":"597b2e8c909f050004000103","label":"sport","page":"AWD0003rpz","page_number":9,"page_order":38,"page_type":"diary","place":"Cologne","subject_id":"59539e059d936f003e00396f","time":"","type":"domestic","votes":{},"x":25,"y":70},{"compare":"3JUN1919","coords":[0.0,0.0],"count":3,"date":"3 Jun 1919","datetime":"1919-06-03T00:00:00.000Z","group":"GWD00000r0","hit_rate":0.6,"id":"597b2e8c909f050004000107","label":"3 Jun 1919","page":"AWD0003rpw","page_number":10,"page_order":1,"page_type":"diary","place":"Cologne","subject_id":"59539e059d936f003e00396b","time":"","type":"diaryDate","votes":{"day":["3"],"month":["Jun"],"year":["1919"]},"x":6,"y":22},{"compare":"BOLOGNE","coords":[0.0,0.0],"count":2,"date":"3 Jun 1919","datetime":"1919-06-03T00:00:00.000Z","group":"GWD00000r0","hit_rate":0.4,"id":"597b2e8c909f050004000109","label":"Cologne, Bologne","page":"AWD0003rpw","page_number":10,"page_order":3,"page_type":"diary","place":"Cologne, Bologne","subject_id":"59539e059d936f003e00396b","time":"","type":"place","votes":{"place":["Cologne","Bologne"],"location":["true"],"name":["Kln","Bologne"],"lat":["50.93333","48.20005"],"long":["6.95","5.14209"],"id":["2886242","3031862"]},"x":8,"y":25},{"compare":"3JUL1919","coords":[0.0,0.0],"count":2,"date":"3 Jun,Jul 1919","group":"GWD00000r0","hit_rate":0.4,"id":"597b2e8c909f05000400010a","label":"3 Jun,Jul 1919","page":"AWD0003rpw","page_number":10,"page_order":4,"page_type":"diary","place":"Cologne, Bologne","subject_id":"59539e059d936f003e00396b","time":"","type":"diaryDate","votes":{"day":["3"],"month":["Jun","Jul"],"year":["1919"]},"x":6,"y":27},{"compare":"PARADES","coords":[0.0,0.0],"count":4,"date":"3 Jun,Jul 1919","group":"GWD00000r0","hit_rate":0.8,"id":"597b2e8c909f05000400010c","label":"parades","page":"AWD0003rpw","page_number":10,"page_order":6,"page_type":"diary","place":"Cologne, Bologne","subject_id":"59539e059d936f003e00396b","time":"","type":"domestic","votes":{},"x":31,"y":27},{"compare":"4JUN1919","coords":[0.0,0.0],"count":2,"date":"4 Jun 1919","datetime":"1919-06-04T00:00:00.000Z","group":"GWD00000r0","hit_rate":0.4,"id":"597b2e8c909f05000400010d","label":"4 Jun 1919","page":"AWD0003rpw","page_number":10,"page_order":7,"page_type":"diary","place":"Cologne, Bologne","subject_id":"59539e059d936f003e00396b","time":"","type":"diaryDate","votes":{"day":["4"],"month":["Jun"],"year":["1919"]},"x":6,"y":33},{"compare":"COLOGNE","coords":[6.95,50.93333],"count":2,"date":"4 Jun 1919","datetime":"1919-06-04T00:00:00.000Z","group":"GWD00000r0","hit_rate":0.4,"id":"597b2e8c909f05000400010e","label":"Cologne","page":"AWD0003rpw","page_number":10,"page_order":8,"page_type":"diary","place":"Cologne","subject_id":"59539e059d936f003e00396b","time":"","type":"place","votes":{"place":["Cologne"],"location":["true"],"name":["Kln"],"lat":["50.93333"],"long":["6.95"],"id":["2886242"]},"x":9,"y":35},{"compare":"BJCURLING","coords":[6.95,50.93333],"count":3,"date":"4 Jun 1919","datetime":"1919-06-04T00:00:00.000Z","group":"GWD00000r0","hit_rate":0.6,"id":"597b2e8c909f05000400010f","label":"Lieutenant Colonel B J,BJ, Curling","page":"AWD0003rpw","page_number":10,"page_order":9,"page_type":"diary","place":"Cologne","subject_id":"59539e059d936f003e00396b","time":"","type":"person","votes":{"first":["B J","BJ",""],"surname":["Curling"],"rank":["Lieutenant Colonel"],"number":[""],"reason":["departed_posted"],"unit":[""]},"x":32,"y":35},{"compare":"JSUNTHANK","coords":[6.95,50.93333],"count":3,"date":"4 Jun 1919","datetime":"1919-06-04T00:00:00.000Z","group":"GWD00000r0","hit_rate":0.6,"id":"597b2e8c909f050004000110","label":"Major J S Unthank","page":"AWD0003rpw","page_number":10,"page_order":10,"page_type":"diary","place":"Cologne","subject_id":"59539e059d936f003e00396b","time":"","type":"person","votes":{"first":["J S"],"surname":["Unthank"],"rank":["Major"],"number":[""],"reason":["commander"],"unit":[""]},"x":80,"y":35},{"compare":"5JUN1919","coords":[6.95,50.93333],"count":2,"date":"5 Jun 1919","datetime":"1919-06-05T00:00:00.000Z","group":"GWD00000r0","hit_rate":0.4,"id":"597b2e8c909f050004000111","label":"5 Jun 1919","page":"AWD0003rpw","page_number":10,"page_order":11,"page_type":"diary","place":"Cologne","subject_id":"59539e059d936f003e00396b","time":"","type":"diaryDate","votes":{"day":["5"],"month":["Jun"],"year":["1919"]},"x":6,"y":37},{"compare":"SPORT","coords":[6.95,50.93333],"count":3,"date":"5 Jun 1919","datetime":"1919-06-05T00:00:00.000Z","group":"GWD00000r0","hit_rate":0.4,"id":"597b2e8c909f050004000112","label":"sport","page":"AWD0003rpw","page_number":10,"page_order":12,"page_type":"diary","place":"Cologne","subject_id":"59539e059d936f003e00396b","time":"","type":"domestic","votes":{},"x":78,"y":39},{"compare":"6JUN1919","coords":[6.95,50.93333],"count":2,"date":"6 Jun 1919","datetime":"1919-06-06T00:00:00.000Z","group":"GWD00000r0","hit_rate":0.4,"id":"597b2e8c909f050004000114","label":"6 Jun 1919","page":"AWD0003rpw","page_number":10,"page_order":14,"page_type":"diary","place":"Cologne","subject_id":"59539e059d936f003e00396b","time":"","type":"diaryDate","votes":{"day":["6"],"month":["Jun"],"year":["1919"]},"x":6,"y":42},{"compare":"COLOGNE","coords":[6.95,50.93333],"count":2,"date":"6 Jun 1919","datetime":"1919-06-06T00:00:00.000Z","group":"GWD00000r0","hit_rate":0.4,"id":"597b2e8c909f050004000115","label":"Cologne","page":"AWD0003rpw","page_number":10,"page_order":15,"page_type":"diary","place":"Cologne","subject_id":"59539e059d936f003e00396b","time":"","type":"place","votes":{"place":["Cologne"],"location":["true"],"name":["Kln"],"lat":["50.93333"],"long":["6.95"],"id":["2886242"]},"x":8,"y":44},{"compare":"7JUN1919","coords":[6.95,50.93333],"count":2,"date":"7 Jun 1919","datetime":"1919-06-07T00:00:00.000Z","group":"GWD00000r0","hit_rate":0.4,"id":"597b2e8c909f050004000119","label":"7 Jun 1919","page":"AWD0003rpw","page_number":10,"page_order":19,"page_type":"diary","place":"Cologne","subject_id":"59539e059d936f003e00396b","time":"","type":"diaryDate","votes":{"day":["7"],"month":["Jun"],"year":["1919"]},"x":6,"y":45},{"compare":"JSUNTHANK","coords":[6.95,50.93333],"count":3,"date":"7 Jun 1919","datetime":"1919-06-07T00:00:00.000Z","group":"GWD00000r0","hit_rate":0.6,"id":"597b2e8c909f05000400011b","label":"Major J S Unthank","page":"AWD0003rpw","page_number":10,"page_order":21,"page_type":"diary","place":"Cologne","subject_id":"59539e059d936f003e00396b","time":"","type":"person","votes":{"first":["J S"],"surname":["Unthank"],"rank":["Major"],"number":[""],"reason":["departed_leave"],"unit":[""]},"x":27,"y":48},{"compare":"TGDAVIDSON","coords":[6.95,50.93333],"count":3,"date":"7 Jun 1919","datetime":"1919-06-07T00:00:00.000Z","group":"GWD00000r0","hit_rate":0.6,"id":"597b2e8c909f05000400011c","label":"Major J G Davidson","page":"AWD0003rpw","page_number":10,"page_order":22,"page_type":"diary","place":"Cologne","subject_id":"59539e059d936f003e00396b","time":"","type":"person","votes":{"first":["J G"],"surname":["Davidson"],"rank":["Major"],"number":[""],"reason":["commander"],"unit":[""]},"x":75,"y":49},{"compare":"9JUN1919","coords":[6.95,50.93333],"count":2,"date":"9 Jun 1919","datetime":"1919-06-09T00:00:00.000Z","group":"GWD00000r0","hit_rate":0.4,"id":"597b2e8c909f05000400011d","label":"9 Jun 1919","page":"AWD0003rpw","page_number":10,"page_order":23,"page_type":"diary","place":"Cologne","subject_id":"59539e059d936f003e00396b","time":"","type":"diaryDate","votes":{"day":["9"],"month":["Jun"],"year":["1919"]},"x":6,"y":54},{"compare":"COLOGNE","coords":[6.95,50.93333],"count":2,"date":"9 Jun 1919","datetime":"1919-06-09T00:00:00.000Z","group":"GWD00000r0","hit_rate":0.4,"id":"597b2e8c909f05000400011f","label":"Cologne","page":"AWD0003rpw","page_number":10,"page_order":25,"page_type":"diary","place":"Cologne","subject_id":"59539e059d936f003e00396b","time":"","type":"place","votes":{"place":["Cologne"],"location":["true"],"name":["Kln"],"lat":["50.93333"],"long":["6.95"],"id":["2886242"]},"x":8,"y":57},{"compare":"10JUN1919","coords":[6.95,50.93333],"count":2,"date":"10 Jun 1919","datetime":"1919-06-10T00:00:00.000Z","group":"GWD00000r0","hit_rate":0.4,"id":"597b2e8c909f050004000121","label":"10 Jun 1919","page":"AWD0003rpw","page_number":10,"page_order":27,"page_type":"diary","place":"Cologne","subject_id":"59539e059d936f003e00396b","time":"","type":"diaryDate","votes":{"day":["10"],"month":["Jun"],"year":["1919"]},"x":6,"y":59},{"compare":"SPORT","coords":[6.95,50.93333],"count":3,"date":"10 Jun 1919","datetime":"1919-06-10T00:00:00.000Z","group":"GWD00000r0","hit_rate":0.6,"id":"597b2e8c909f050004000122","label":"sport","page":"AWD0003rpw","page_number":10,"page_order":28,"page_type":"diary","place":"Cologne","subject_id":"59539e059d936f003e00396b","time":"","type":"domestic","votes":{},"x":23,"y":59},{"compare":"11JUN1919","coords":[6.95,50.93333],"count":2,"date":"11 Jun 1919","datetime":"1919-06-11T00:00:00.000Z","group":"GWD00000r0","hit_rate":0.4,"id":"597b2e8c909f050004000125","label":"11 Jun 1919","page":"AWD0003rpw","page_number":10,"page_order":31,"page_type":"diary","place":"Cologne","subject_id":"59539e059d936f003e00396b","time":"","type":"diaryDate","votes":{"day":["11"],"month":["Jun"],"year":["1919"]},"x":6,"y":62},{"compare":"BJCURLING","coords":[6.95,50.93333],"count":3,"date":"11 Jun 1919","datetime":"1919-06-11T00:00:00.000Z","group":"GWD00000r0","hit_rate":0.6,"id":"597b2e8c909f050004000126","label":"Lieutenant Colonel BJ Curling","page":"AWD0003rpw","page_number":10,"page_order":32,"page_type":"diary","place":"Cologne","subject_id":"59539e059d936f003e00396b","time":"","type":"person","votes":{"first":["BJ"],"surname":["Curling"],"rank":["Lieutenant Colonel"],"number":[""],"reason":["returned_posted"],"unit":[""]},"x":29,"y":64},{"compare":"COLOGNE","coords":[6.95,50.93333],"count":2,"date":"11 Jun 1919","datetime":"1919-06-11T00:00:00.000Z","group":"GWD00000r0","hit_rate":0.4,"id":"597b2e8c909f050004000127","label":"Cologne","page":"AWD0003rpw","page_number":10,"page_order":33,"page_type":"diary","place":"Cologne","subject_id":"59539e059d936f003e00396b","time":"","type":"place","votes":{"place":["Cologne"],"location":["true"],"name":["Kln"],"lat":["50.93333"],"long":["6.95"],"id":["2886242"]},"x":8,"y":65},{"compare":"12JUN1919","coords":[6.95,50.93333],"count":2,"date":"12 Jun 1919","datetime":"1919-06-12T00:00:00.000Z","group":"GWD00000r0","hit_rate":0.4,"id":"597b2e8c909f050004000128","label":"12 Jun 1919","page":"AWD0003rpw","page_number":10,"page_order":34,"page_type":"diary","place":"Cologne","subject_id":"59539e059d936f003e00396b","time":"","type":"diaryDate","votes":{"day":["12"],"month":["Jun"],"year":["1919"]},"x":6,"y":66},{"compare":"INSPECTIONS","coords":[6.95,50.93333],"count":2,"date":"12 Jun 1919","datetime":"1919-06-12T00:00:00.000Z","group":"GWD00000r0","hit_rate":0.4,"id":"597b2e8c909f050004000129","label":"inspections","page":"AWD0003rpw","page_number":10,"page_order":35,"page_type":"diary","place":"Cologne","subject_id":"59539e059d936f003e00396b","time":"","type":"domestic","votes":{},"x":37,"y":69},{"compare":"SPORT","coords":[6.95,50.93333],"count":3,"date":"12 Jun 1919","datetime":"1919-06-12T00:00:00.000Z","group":"GWD00000r0","hit_rate":0.4,"id":"597b2e8c909f05000400012b","label":"sport","page":"AWD0003rpw","page_number":10,"page_order":37,"page_type":"diary","place":"Cologne","subject_id":"59539e059d936f003e00396b","time":"","type":"domestic","votes":{},"x":76,"y":70},{"compare":"14JUN1919","coords":[6.95,50.93333],"count":2,"date":"14 Jun 1919","datetime":"1919-06-14T00:00:00.000Z","group":"GWD00000r0","hit_rate":0.2,"id":"597b2e8c909f05000400012c","label":"14 Jun 1919","page":"AWD0003rpw","page_number":10,"page_order":38,"page_type":"diary","place":"Cologne","subject_id":"59539e059d936f003e00396b","time":"","type":"diaryDate","votes":{"day":["14"],"month":["Jun"],"year":["1919"]},"x":6,"y":75},{"compare":"MCGUCHIN","coords":[6.95,50.93333],"count":2,"date":"14 Jun 1919","datetime":"1919-06-14T00:00:00.000Z","group":"GWD00000r0","hit_rate":0.4,"id":"597b2e8c909f05000400012d","label":"Captain  McGruhin, McGuchin","page":"AWD0003rpw","page_number":10,"page_order":39,"page_type":"diary","place":"Cologne","subject_id":"59539e059d936f003e00396b","time":"","type":"person","votes":{"first":[""],"surname":["McGruhin","McGuchin"],"rank":["Captain"],"number":[""],"reason":["departed_leave"],"unit":["","RAMC"]},"x":25,"y":77},{"compare":"COLOGNE","coords":[6.95,50.93333],"count":2,"date":"14 Jun 1919","datetime":"1919-06-14T00:00:00.000Z","group":"GWD00000r0","hit_rate":0.4,"id":"597b2e8c909f05000400012f","label":"Cologne","page":"AWD0003rpw","page_number":10,"page_order":41,"page_type":"diary","place":"Cologne","subject_id":"59539e059d936f003e00396b","time":"","type":"place","votes":{"place":["Cologne"],"location":["true"],"name":["Kln"],"lat":["50.93333"],"long":["6.95"],"id":["2886242"]},"x":8,"y":78},{"compare":"15JUN1919","coords":[6.95,50.93333],"count":2,"date":"15 Jun 1919","datetime":"1919-06-15T00:00:00.000Z","group":"GWD00000r0","hit_rate":0.4,"id":"597b2e8c909f050004000130","label":"15 Jun 1919","page":"AWD0003rpw","page_number":10,"page_order":42,"page_type":"diary","place":"Cologne","subject_id":"59539e059d936f003e00396b","time":"","type":"diaryDate","votes":{"day":["15"],"month":["Jun"],"year":["1919"]},"x":6,"y":79},{"compare":"DGTULLY","coords":[6.95,50.93333],"count":3,"date":"15 Jun 1919","datetime":"1919-06-15T00:00:00.000Z","group":"GWD00000r0","hit_rate":0.6,"id":"597b2e8c909f050004000131","label":"Captain D G Tully","page":"AWD0003rpw","page_number":10,"page_order":43,"page_type":"diary","place":"Cologne","subject_id":"59539e059d936f003e00396b","time":"","type":"person","votes":{"first":["D G"],"surname":["Tully"],"rank":["Captain"],"number":[""],"reason":["departed_leave"],"unit":[""]},"x":28,"y":81},{"compare":"17JUN1919","coords":[6.95,50.93333],"count":2,"date":"17 Jun 1919","datetime":"1919-06-17T00:00:00.000Z","group":"GWD00000r0","hit_rate":0.4,"id":"597b2e8c909f050004000132","label":"17 Jun 1919","page":"AWD0003rpw","page_number":10,"page_order":44,"page_type":"diary","place":"Cologne","subject_id":"59539e059d936f003e00396b","time":"","type":"diaryDate","votes":{"day":["17"],"month":["Jun"],"year":["1919"]},"x":6,"y":83},{"compare":"COLOGNE","coords":[6.95,50.93333],"count":2,"date":"17 Jun 1919","datetime":"1919-06-17T00:00:00.000Z","group":"GWD00000r0","hit_rate":0.4,"id":"597b2e8c909f050004000133","label":"Cologne","page":"AWD0003rpw","page_number":10,"page_order":45,"page_type":"diary","place":"Cologne","subject_id":"59539e059d936f003e00396b","time":"","type":"place","votes":{"place":["Cologne"],"location":["true"],"name":["Kln"],"lat":["50.93333"],"long":["6.95"],"id":["2886242"]},"x":7,"y":86},{"compare":"18JUN1919","coords":[6.95,50.93333],"count":3,"date":"18 Jun 1919","datetime":"1919-06-18T00:00:00.000Z","group":"GWD00000r0","hit_rate":0.2,"id":"597b2e8c909f050004000134","label":"18 Jun 1919","page":"AWD0003rpw","page_number":10,"page_order":46,"page_type":"diary","place":"Cologne","subject_id":"59539e059d936f003e00396b","time":"","type":"diaryDate","votes":{"day":["18"],"month":["Jun"],"year":["1919"]},"x":6,"y":88},{"compare":"19JUN1919","coords":[6.95,50.93333],"count":4,"date":"19 Jun 1919","datetime":"1919-06-19T00:00:00.000Z","group":"GWD00000r0","hit_rate":0.8,"id":"597b2e8c909f050004000138","label":"19 Jun 1919","page":"AWD0003rpv","page_number":11,"page_order":3,"page_type":"diary","place":"Cologne","subject_id":"59539e059d936f003e003977","time":"","type":"diaryDate","votes":{"day":["19"],"month":["Jun"],"year":["1919"]},"x":6,"y":25},{"compare":"0800AM","coords":[6.95,50.93333],"count":3,"date":"19 Jun 1919","datetime":"1919-06-19T08:00:00.000Z","group":"GWD00000r0","hit_rate":0.6,"id":"597b2e8c909f05000400013b","label":"0800AM","page":"AWD0003rpv","page_number":11,"page_order":6,"page_type":"diary","place":"Cologne","subject_id":"59539e059d936f003e003977","time":"0800AM","type":"time","votes":{},"x":65,"y":27},{"compare":"WERMELSKIRCHEN","coords":[6.95,50.93333],"count":2,"date":"19 Jun 1919","datetime":"1919-06-19T08:00:00.000Z","group":"GWD00000r0","hit_rate":0.2,"id":"597b2e8c909f05000400013c","label":"Wermelskirchen","page":"AWD0003rpv","page_number":11,"page_order":7,"page_type":"diary","place":"Cologne","subject_id":"59539e059d936f003e003977","time":"0800AM","type":"place","votes":{"place":["Wermelskirchen"],"location":["true","false"],"name":["Wermelskirchen"],"lat":["51.1397"],"long":["7.21583"],"id":["2810855"]},"x":53,"y":28},{"compare":"OFFICER22OTHER647","coords":[6.95,50.93333],"count":3,"date":"19 Jun 1919","datetime":"1919-06-19T08:00:00.000Z","group":"GWD00000r0","hit_rate":0.6,"id":"597b2e8c909f05000400013f","label":"officer: 22, other: 647","page":"AWD0003rpv","page_number":11,"page_order":10,"page_type":"diary","place":"Cologne","subject_id":"59539e059d936f003e003977","time":"0800AM","type":"strength","votes":{},"x":55,"y":32},{"compare":"DABRINGHAUSENSTRASSEWERMELSKIRCHENGERMANY","coords":[6.95,50.93333],"count":2,"date":"19 Jun 1919","datetime":"1919-06-19T08:00:00.000Z","group":"GWD00000r0","hit_rate":0.4,"id":"597b2e8c909f050004000142","label":" Da[b]ringhaus[en] Strasse, Wermelskirchen, Germany","page":"AWD0003rpv","page_number":11,"page_order":13,"page_type":"diary","place":"Cologne","subject_id":"59539e059d936f003e003977","time":"0800AM","type":"place","votes":{"place":[" Da[b]ringhaus[en] Strasse, Wermelskirchen, Germany"],"location":["false"],"name":[""],"lat":[""],"long":[""],"id":[""]},"x":53,"y":37},{"compare":"DABRINGHAUSEN","coords":[7.19,51.09052],"count":2,"date":"19 Jun 1919","datetime":"1919-06-19T08:00:00.000Z","group":"GWD00000r0","hit_rate":0.4,"id":"597b2e8c909f050004000143","label":"Dabringhausen","page":"AWD0003rpv","page_number":11,"page_order":14,"page_type":"diary","place":"Dabringhausen","subject_id":"59539e059d936f003e003977","time":"0800AM","type":"place","votes":{"place":["Dabringhausen"],"location":["true"],"name":["Dabringhausen"],"lat":["51.09052"],"long":["7.19"],"id":["2939628"]},"x":45,"y":38},{"compare":"20JUN1919","coords":[7.19,51.09052],"count":3,"date":"20 Jun 1919","datetime":"1919-06-20T00:00:00.000Z","group":"GWD00000r0","hit_rate":0.2,"id":"597b2e8c909f050004000145","label":"20 Jun 1919","page":"AWD0003rpv","page_number":11,"page_order":16,"page_type":"diary","place":"Dabringhausen","subject_id":"59539e059d936f003e003977","time":"","type":"diaryDate","votes":{"day":["20"],"month":["Jun"],"year":["1919"]},"x":6,"y":42},{"compare":"WERMELSKIRCHEN","coords":[7.21583,51.1397],"count":2,"date":"20 Jun 1919","datetime":"1919-06-20T00:00:00.000Z","group":"GWD00000r0","hit_rate":0.4,"id":"597b2e8c909f050004000147","label":"Wermelskirchen","page":"AWD0003rpv","page_number":11,"page_order":18,"page_type":"diary","place":"Wermelskirchen","subject_id":"59539e059d936f003e003977","time":"","type":"place","votes":{"place":["Wermelskirchen"],"location":["true"],"name":["Wermelskirchen"],"lat":["51.1397"],"long":["7.21583"],"id":["2810855"]},"x":9,"y":45},{"compare":"21JUN1919","coords":[7.21583,51.1397],"count":3,"date":"21 Jun 1919","datetime":"1919-06-21T00:00:00.000Z","group":"GWD00000r0","hit_rate":0.6,"id":"597b2e8c909f05000400014a","label":"21 Jun 1919","page":"AWD0003rpv","page_number":11,"page_order":21,"page_type":"diary","place":"Wermelskirchen","subject_id":"59539e059d936f003e003977","time":"","type":"diaryDate","votes":{"day":["21"],"month":["Jun"],"year":["1919"]},"x":6,"y":46},{"compare":"MCGRUCHIN","coords":[7.21583,51.1397],"count":2,"date":"21 Jun 1919","datetime":"1919-06-21T00:00:00.000Z","group":"GWD00000r0","hit_rate":0.4,"id":"597b2e8c909f05000400014b","label":"Captain  McGelchin, McGruchin","page":"AWD0003rpv","page_number":11,"page_order":22,"page_type":"diary","place":"Wermelskirchen","subject_id":"59539e059d936f003e003977","time":"","type":"person","votes":{"first":[""],"surname":["McGelchin","McGruchin"],"rank":["Captain"],"number":[""],"reason":["returned_leave"],"unit":[""]},"x":72,"y":48},{"compare":"26JUN1919","coords":[7.21583,51.1397],"count":3,"date":"26 Jun 1919","datetime":"1919-06-26T00:00:00.000Z","group":"GWD00000r0","hit_rate":0.6,"id":"597b2e8c909f05000400014c","label":"26 Jun 1919","page":"AWD0003rpv","page_number":11,"page_order":23,"page_type":"diary","place":"Wermelskirchen","subject_id":"59539e059d936f003e003977","time":"","type":"diaryDate","votes":{"day":["26"],"month":["Jun"],"year":["1919"]},"x":6,"y":50},{"compare":"CARTWRIGHT","coords":[7.21583,51.1397],"count":2,"date":"26 Jun 1919","datetime":"1919-06-26T00:00:00.000Z","group":"GWD00000r0","hit_rate":0.4,"id":"597b2e8c909f05000400014e","label":"Private  Carroright, Cartwright","page":"AWD0003rpv","page_number":11,"page_order":25,"page_type":"diary","place":"Wermelskirchen","subject_id":"59539e059d936f003e003977","time":"","type":"person","votes":{"first":[""],"surname":["Carroright","Cartwright"],"rank":["Private"],"number":[""],"reason":["other"],"unit":[""]},"x":58,"y":52},{"compare":"27JUN1919","coords":[7.21583,51.1397],"count":3,"date":"27 Jun 1919","datetime":"1919-06-27T00:00:00.000Z","group":"GWD00000r0","hit_rate":0.6,"id":"597b2e8c909f050004000150","label":"27 Jun 1919","page":"AWD0003rpv","page_number":11,"page_order":27,"page_type":"diary","place":"Wermelskirchen","subject_id":"59539e059d936f003e003977","time":"","type":"diaryDate","votes":{"day":["27"],"month":["Jun"],"year":["1919"]},"x":6,"y":59},{"compare":"WERMELSKIRCHEN","coords":[7.21583,51.1397],"count":2,"date":"27 Jun 1919","datetime":"1919-06-27T00:00:00.000Z","group":"GWD00000r0","hit_rate":0.4,"id":"597b2e8d909f050004000152","label":"Wermelskirchen","page":"AWD0003rpv","page_number":11,"page_order":29,"page_type":"diary","place":"Wermelskirchen","subject_id":"59539e059d936f003e003977","time":"","type":"place","votes":{"place":["Wermelskirchen"],"location":["true"],"name":["Wermelskirchen"],"lat":["51.1397"],"long":["7.21583"],"id":["2810855"]},"x":8,"y":60},{"compare":"28JUN1919","coords":[7.21583,51.1397],"count":3,"date":"28 Jun 1919","datetime":"1919-06-28T00:00:00.000Z","group":"GWD00000r0","hit_rate":0.6,"id":"597b2e8d909f050004000154","label":"28 Jun 1919","page":"AWD0003rpv","page_number":11,"page_order":31,"page_type":"diary","place":"Wermelskirchen","subject_id":"59539e059d936f003e003977","time":"","type":"diaryDate","votes":{"day":["28"],"month":["Jun"],"year":["1919"]},"x":6,"y":63},{"compare":"29JUN1919","coords":[7.21583,51.1397],"count":4,"date":"29 Jun 1919","datetime":"1919-06-29T00:00:00.000Z","group":"GWD00000r0","hit_rate":0.8,"id":"597b2e8d909f050004000155","label":"29 Jun 1919","page":"AWD0003rpv","page_number":11,"page_order":32,"page_type":"diary","place":"Wermelskirchen","subject_id":"59539e059d936f003e003977","time":"","type":"diaryDate","votes":{"day":["29"],"month":["Jun"],"year":["1919"]},"x":6,"y":67},{"compare":"PARADES","coords":[7.21583,51.1397],"count":3,"date":"29 Jun 1919","datetime":"1919-06-29T00:00:00.000Z","group":"GWD00000r0","hit_rate":0.6,"id":"597b2e8d909f050004000157","label":"parades","page":"AWD0003rpv","page_number":11,"page_order":34,"page_type":"diary","place":"Wermelskirchen","subject_id":"59539e059d936f003e003977","time":"","type":"domestic","votes":{},"x":27,"y":68},{"compare":"30JUN1919","coords":[7.21583,51.1397],"count":3,"date":"30 Jun 1919","datetime":"1919-06-30T00:00:00.000Z","group":"GWD00000r0","hit_rate":0.6,"id":"597b2e8d909f050004000159","label":"30 Jun 1919","page":"AWD0003rpv","page_number":11,"page_order":36,"page_type":"diary","place":"Wermelskirchen","subject_id":"59539e059d936f003e003977","time":"","type":"diaryDate","votes":{"day":["30"],"month":["Jun"],"year":["1919"]},"x":6,"y":75},{"compare":"MOVEMENT","coords":[7.21583,51.1397],"count":2,"date":"30 Jun 1919","datetime":"1919-06-30T00:00:00.000Z","group":"GWD00000r0","hit_rate":0.4,"id":"597b2e8d909f05000400015b","label":"movement","page":"AWD0003rpv","page_number":11,"page_order":38,"page_type":"diary","place":"Wermelskirchen","subject_id":"59539e059d936f003e003977","time":"","type":"activity","votes":{},"x":27,"y":78}]
