{"categories":[],"classification_count":1196,"created_at":"2016-07-07T20:57:41.999Z","id":"577e8d703ae7403a580008f2","metadata":{"id":"C7354045","source":"wo/95/2510/4","year":1915,"diary_number":4,"page_offset":491,"start_date":"1915-10-01T00:00:00.000Z","end_date":"1918-01-31T00:00:00.000Z"},"name":"109 Infantry Brigade, 10 Battalion Royal Inniskilling Fusiliers","project_id":"52d065303ae740380a000001","project_name":"war_diary","random":0.048348114876199055,"state":"complete","stats":{"active":0,"complete":237,"disabled":0,"inactive":0,"paused":0,"total":237},"updated_at":"2016-07-07T20:57:42.044Z","zooniverse_id":"GWD00000ob"}
